Workbook
Name holidays: Holidays!$A$2:$A$500

Sheet Actual Revenue
A1: Year | B1: Revenue Code | C1: Description | D1: January | E1: February | F1: March | G1: April | H1: May | I1: June | J1: July | K1: August | L1: September | M1: October | N1: November | O1: December | P1: Total | S1: Instructions
A2: 2020 | B2: 1001.01.00 | C2: =_xlfn.XLOOKUP(B2, 'Revenue Codes'!$A$2:$A$99, 'Revenue Codes'!$B$2:$B$99, "") -> Import Duty | D2: 8.5698624e+09 | E2: 8.1488102e+09 | F2: 5.1729912e+09 | G2: 9.3749773e+09 | H2: 6.0418605e+09 | I2: 1.0288255e+10 | J2: 1.282454e+10 | K2: 1.2749402e+10 | L2: 1.1761995e+10 | M2: 12264343587 | N2: 7066693261 | O2: 9165036084 | P2: =SUM(D2:O2) -> 1.1342877e+11 | S2: 1) Revenue Code description appears automatically when code is entered. If code does not appear, add a new Revenue Code in the relevant Excel Sheet. 2) Fields automatically turns red if negative values are entered. Check and verify if those values are correct. 3) Enter all values in exact figures LKR (Not is millions, '000, billion etc.) 4) Values entered in this shared Excel automatically updates the Revenue Dashboard. If any errors in the dashboard is noticed, check values in this Excel Sheet.
A3: 2020 | B3: 1001.02.00 | C3: =_xlfn.XLOOKUP(B3, 'Revenue Codes'!$A$2:$A$99, 'Revenue Codes'!$B$2:$B$99, "") -> Export Duty | D3: 8894271 | E3: 87156406 | F3: 4115423 | G3: 1706001 | H3: 82998001 | I3: -138833998 | J3: 25531227 | K3: 3535255 | L3: 3505754 | M3: 4284650 | N3: 794437 | O3: 96015303 | P3: =SUM(D3:O3) -> 179702730
A4: 2020 | B4: 1001.04.00 | C4: =_xlfn.XLOOKUP(B4, 'Revenue Codes'!$A$2:$A$99, 'Revenue Codes'!$B$2:$B$99, "") -> PAL | D4: 11977905682 | E4: 11303190126 | F4: 6371475697 | G4: 7512095455 | H4: 6951258425 | I4: 8473303494 | J4: 9856600239 | K4: 9323097028 | L4: 11113490909 | M4: 9962682984 | N4: 10496612878 | O4: 12100297636 | P4: =SUM(D4:O4) -> 115442010553
A5: 2020 | B5: 1001.05.01 | C5: =_xlfn.XLOOKUP(B5, 'Revenue Codes'!$A$2:$A$99, 'Revenue Codes'!$B$2:$B$99, "") -> Cess (Import) | D5: 5113629670 | E5: 4282966641 | F5: 7700543 | G5: 2778891471 | H5: 23941893 | I5: 9495722328 | J5: 5245838886 | K5: 2958589037 | L5: 3906326327 | M5: 3786699039 | N5: 4211884531 | O5: 5482934475 | P5: =SUM(D5:O5) -> 47295124841
A6: 2020 | B6: 1001.05.02 | C6: =_xlfn.XLOOKUP(B6, 'Revenue Codes'!$A$2:$A$99, 'Revenue Codes'!$B$2:$B$99, "") -> Cess (Export) | D6: 194168144 | E6: 92704118 | F6: 135204071 | G6: 87177765 | H6: 93382308 | I6: 344202277 | J6: 201787371 | K6: 230506868 | L6: 193032472 | M6: 117640702 | N6: 4833073 | O6: 235979290 | P6: =SUM(D6:O6) -> 1930618459
A7: 2020 | B7: 1001.06.00 | C7: =_xlfn.XLOOKUP(B7, 'Revenue Codes'!$A$2:$A$99, 'Revenue Codes'!$B$2:$B$99, "") -> Motor Vehicle (Conc.) Levy | D7: 3964401 | E7: 204088 | F7: 3899753 | I7: 1743025 | J7: -9811267 | K7: -2161500 | L7: 2161500 | N7: 313387 | O7: 2167363 | P7: =SUM(D7:O7) -> 2480750
A8: 2020 | B8: 1001.08.00 | C8: =_xlfn.XLOOKUP(B8, 'Revenue Codes'!$A$2:$A$99, 'Revenue Codes'!$B$2:$B$99, "") -> SCL | D8: 6153276217 | E8: 7294943259 | F8: 5818567445 | G8: 4825369566 | H8: 5172522400 | I8: 6894182726 | J8: 10305499874 | K8: 8677060214 | L8: 10419136367 | M8: 7499205343 | N8: 3917141784 | O8: 5732047773 | P8: =SUM(D8:O8) -> 82708952968
A9: 2020 | B9: 1003.01.00 | C9: =_xlfn.XLOOKUP(B9, 'Revenue Codes'!$A$2:$A$99, 'Revenue Codes'!$B$2:$B$99, "") -> LXT | D9: 61026434 | E9: 124797947 | F9: 57493116 | G9: 248458011 | H9: 332450594 | I9: 72154212 | J9: 47859220 | K9: 46135522 | L9: 2168716 | M9: 1576799 | N9: 316665 | O9: 45630 | P9: =SUM(D9:O9) -> 994482866
A10: 2020 | B10: 1002.01.04 | C10: =_xlfn.XLOOKUP(B10, 'Revenue Codes'!$A$2:$A$99, 'Revenue Codes'!$B$2:$B$99, "") -> VAT | D10: 9454699025 | E10: 7367278740 | F10: 6018829396 | G10: 6052997708 | H10: 5008431637 | I10: 4805787671 | J10: 6845220858 | K10: 6072915421 | L10: 8849874653 | M10: 8292903439 | N10: 7549846915 | O10: 9405505341 | P10: =SUM(D10:O10) -> 85724290804
A11: 2020 | B11: 1002.05.00 | C11: =_xlfn.XLOOKUP(B11, 'Revenue Codes'!$A$2:$A$99, 'Revenue Codes'!$B$2:$B$99, "") -> Excise (Spec. Prov.) Levy | L11: 1514969592 | M11: 954272875 | N11: 690098340 | O11: 679609534 | P11: =SUM(D11:O11) -> 3838950341
A12: 2020 | B12: 1002.05.01 | C12: =_xlfn.XLOOKUP(B12, 'Revenue Codes'!$A$2:$A$99, 'Revenue Codes'!$B$2:$B$99, "") -> Cigarette | D12: 8045498721 | E12: 9011085300 | F12: 10824314847 | G12: 5986363600 | H12: 7085634316 | I12: 2490105353 | J12: 4840166084 | K12: 10665599200 | L12: 7128381110 | M12: 12471212300 | N12: 8199679800 | O12: 7596503488 | P12: =SUM(D12:O12) -> 94344544119
A13: 2020 | B13: 1002.05.02 | C13: =_xlfn.XLOOKUP(B13, 'Revenue Codes'!$A$2:$A$99, 'Revenue Codes'!$B$2:$B$99, "") -> Liquor | P13: =SUM(D13:O13) -> 0
A14: 2020 | B14: 1002.05.03 | C14: =_xlfn.XLOOKUP(B14, 'Revenue Codes'!$A$2:$A$99, 'Revenue Codes'!$B$2:$B$99, "") -> Petroleum Products | D14: 5796298360 | E14: 8485608221 | F14: 3983643368 | G14: 4248738760 | H14: 2221808479 | I14: 978475238 | J14: 5476079573 | K14: 6143902143 | L14: 4227546817 | M14: 4786810483 | N14: 2788137661 | O14: 119628690 | P14: =SUM(D14:O14) -> 49256677793
A15: 2020 | B15: 1002.05.04 | C15: =_xlfn.XLOOKUP(B15, 'Revenue Codes'!$A$2:$A$99, 'Revenue Codes'!$B$2:$B$99, "") -> Motor Vehicles | D15: 9705892406 | E15: 7335669722 | F15: 7647544424 | G15: 8861560505 | H15: 6477763234 | I15: 1557808849 | J15: 1130608878 | K15: 434254743 | L15: 773077434 | M15: 650652395 | N15: 736657377 | O15: 3448448031 | P15: =SUM(D15:O15) -> 48759937998
A16: 2020 | B16: 1002.05.99 | C16: =_xlfn.XLOOKUP(B16, 'Revenue Codes'!$A$2:$A$99, 'Revenue Codes'!$B$2:$B$99, "") -> Excise (Other) | D16: 476496458 | E16: 447968821 | F16: 114812890 | G16: 841123556 | H16: 148484499 | I16: 91434270 | J16: 497429318 | K16: 227866926 | L16: 400427620 | M16: 925363497 | N16: 81498791 | O16: 474041585 | P16: =SUM(D16:O16) -> 4726948231
A17: 2020 | B17: 1002.12.03 | C17: =_xlfn.XLOOKUP(B17, 'Revenue Codes'!$A$2:$A$99, 'Revenue Codes'!$B$2:$B$99, "") -> NBT | D17: 6656026 | E17: 6198356 | F17: 495552235 | G17: 37092 | H17: 576788 | I17: 5010774 | J17: 10002490 | K17: 302341 | L17: 478048 | M17: 10426620 | N17: 174245 | O17: 771653382 | P17: =SUM(D17:O17) -> 1307068397
A18: 2020 | B18: 1003.06.00 | C18: =_xlfn.XLOOKUP(B18, 'Revenue Codes'!$A$2:$A$99, 'Revenue Codes'!$B$2:$B$99, "") -> ECL | P18: =SUM(D18:O18) -> 0
A19: 2020 | B19: 1003.07.10 | C19: =_xlfn.XLOOKUP(B19, 'Revenue Codes'!$A$2:$A$99, 'Revenue Codes'!$B$2:$B$99, "") -> VEL | D19: 100576000 | E19: 85712548 | F19: 77366350 | G19: 93839000 | H19: 59849000 | I19: 17097000 | J19: 9056994 | K19: 242560456 | L19: 5270000 | M19: 4264200 | N19: 5872880 | O19: 6057426 | P19: =SUM(D19:O19) -> 707521854
A20: 2020 | B20: 1004.04.02 | C20: =_xlfn.XLOOKUP(B20, 'Revenue Codes'!$A$2:$A$99, 'Revenue Codes'!$B$2:$B$99, "") -> ESC | D20: 18599252 | E20: 107896 | F20: 15900 | H20: 5500 | I20: 9155047 | J20: 11474222 | K20: 6495 | L20: 14790 | M20: 65763763 | N20: -64933066 | O20: 2238274 | P20: =SUM(D20:O20) -> 42448073
A21: 2020 | B21: 2003.02.17 | C21: =_xlfn.XLOOKUP(B21, 'Revenue Codes'!$A$2:$A$99, 'Revenue Codes'!$B$2:$B$99, "") -> Sales of Garment | D21: 7116576 | E21: 20765500 | F21: 16273600 | G21: 900 | H21: 5071600 | I21: 6861375 | J21: 13560551 | K21: 19311175 | L21: 37569052 | M21: 28568220 | N21: 13218825 | O21: 16360500 | P21: =SUM(D21:O21) -> 184677874
A22: 2020 | B22: 2003.03.01 | C22: =_xlfn.XLOOKUP(B22, 'Revenue Codes'!$A$2:$A$99, 'Revenue Codes'!$B$2:$B$99, "") -> Fine & Forfeits | D22: -10714746 | E22: 87482592 | F22: 23030550 | G22: -22977704 | H22: 18883062 | I22: 33851159 | J22: 114936870 | K22: 1466640576 | L22: 8.3880759e+08 | M22: 184350837 | N22: 124523863 | O22: 30404000 | P22: =SUM(D22:O22) -> 2.8892186e+09
A23: 2020 | B23: 2003.02.99 | C23: =_xlfn.XLOOKUP(B23, 'Revenue Codes'!$A$2:$A$99, 'Revenue Codes'!$B$2:$B$99, "") -> Sundris & Others | D23: 17456948 | E23: 16831155 | F23: 10440846 | G23: 25295874 | H23: 9390457 | I23: 26282017 | J23: 19570836 | K23: 20575968 | L23: 20344612 | M23: 11744701 | N23: 22728309 | O23: 22390648 | P23: =SUM(D23:O23) -> 223052371
A24: 2020 | B24: 2003.99.00 | C24: =_xlfn.XLOOKUP(B24, 'Revenue Codes'!$A$2:$A$99, 'Revenue Codes'!$B$2:$B$99, "") -> Other Receipts | D24: 14062837 | E24: 12854432 | F24: 13311849 | G24: 4822648 | H24: 4237713 | I24: 7148808 | J24: 5676335 | K24: 5428661 | L24: 7457403 | M24: 7832955 | N24: 7317954 | O24: 17347376 | P24: =SUM(D24:O24) -> 107498971
A25: 2021 | B25: 1001.01.00 | C25: =_xlfn.XLOOKUP(B25, 'Revenue Codes'!$A$2:$A$99, 'Revenue Codes'!$B$2:$B$99, "") -> Import Duty | D25: 1.0060091e+10 | E25: 8.2192255e+09 | F25: 9.5607719e+09 | G25: 3.8040158e+09 | H25: 4.4246346e+09 | I25: 4.7259242e+09 | J25: 1.5572759e+10 | K25: 4.5248436e+09 | L25: -9.0799526e+09 | M25: 3680543867 | N25: 3.6377782e+09 | O25: 5.2086837e+09 | P25: =SUM(D25:O25) -> 6.4339318e+10
A26: 2021 | B26: 1001.02.00 | C26: =_xlfn.XLOOKUP(B26, 'Revenue Codes'!$A$2:$A$99, 'Revenue Codes'!$B$2:$B$99, "") -> Export Duty | D26: 2579082 | E26: 5945931 | F26: 13019171 | G26: 3016285 | H26: 3776831 | I26: 3450473 | J26: 2774288 | K26: 2133936 | L26: 1859767 | M26: 3272925 | N26: 2938189.1 | O26: 2655141 | P26: =SUM(D26:O26) -> 47422019
A27: 2021 | B27: 1001.04.00 | C27: =_xlfn.XLOOKUP(B27, 'Revenue Codes'!$A$2:$A$99, 'Revenue Codes'!$B$2:$B$99, "") -> PAL | D27: 11347077683 | E27: 11305090020 | F27: 14259918777 | G27: 16902272138 | H27: 12577980342 | I27: 1.3115297e+10 | J27: 2.3488919e+08 | K27: 1.2290648e+10 | L27: 2.2101465e+10 | M27: 1.1425529e+10 | N27: 1.2706991e+10 | O27: 1.585809e+10 | P27: =SUM(D27:O27) -> 1.5412525e+11
A28: 2021 | B28: 1001.05.00 | C28: =_xlfn.XLOOKUP(B28, 'Revenue Codes'!$A$2:$A$99, 'Revenue Codes'!$B$2:$B$99, "") -> Cess Levy | E28: 570514 | F28: 2390420 | G28: -2960934 | P28: =SUM(D28:O28) -> 0
A29: 2021 | B29: 1001.05.01 | C29: =_xlfn.XLOOKUP(B29, 'Revenue Codes'!$A$2:$A$99, 'Revenue Codes'!$B$2:$B$99, "") -> Cess (Import) | D29: 5595225410 | E29: 6428597557 | F29: 6948979373 | G29: 7082274768 | H29: 5669275688 | I29: 6.5441158e+09 | J29: 5.9589179e+09 | K29: 5.2491242e+09 | L29: 5.0441933e+09 | M29: 5.3646386e+09 | N29: 6.1793059e+09 | O29: 7255564876 | P29: =SUM(D29:O29) -> 7.3320213e+10
A30: 2021 | B30: 1001.05.02 | C30: =_xlfn.XLOOKUP(B30, 'Revenue Codes'!$A$2:$A$99, 'Revenue Codes'!$B$2:$B$99, "") -> Cess (Export) | D30: 115466623 | E30: 154486610 | F30: 240069407 | G30: 200854802 | H30: 276456834 | I30: 225489295 | J30: 205535276 | K30: 338795592 | L30: 116786158 | M30: -108734173 | N30: 208102609 | O30: 249976629 | P30: =SUM(D30:O30) -> 2223285662
A31: 2021 | B31: 1001.06.00 | C31: =_xlfn.XLOOKUP(B31, 'Revenue Codes'!$A$2:$A$99, 'Revenue Codes'!$B$2:$B$99, "") -> Motor Vehicle (Conc.) Levy | P31: =SUM(D31:O31) -> 0
A32: 2021 | B32: 1001.08.00 | C32: =_xlfn.XLOOKUP(B32, 'Revenue Codes'!$A$2:$A$99, 'Revenue Codes'!$B$2:$B$99, "") -> SCL | D32: 5758218040 | E32: 4454940367 | F32: 5958205721 | G32: 4329117098 | H32: 3930159232 | I32: 3979297951 | J32: 5.374773e+09 | K32: 4050553476 | L32: 4249166867 | M32: 3753900700 | N32: 5336497115 | O32: 4653043396 | P32: =SUM(D32:O32) -> 5.5827873e+10
A33: 2021 | B33: 1003.01.00 | C33: =_xlfn.XLOOKUP(B33, 'Revenue Codes'!$A$2:$A$99, 'Revenue Codes'!$B$2:$B$99, "") -> LXT | E33: 347141385 | F33: 619696 | I33: 46229322 | J33: 0 | K33: 0 | L33: 128214445 | M33: 261751350 | N33: - | O33: -130453288 | P33: =SUM(D33:O33) -> 653502910
A34: 2021 | B34: 1002.01.04 | C34: =_xlfn.XLOOKUP(B34, 'Revenue Codes'!$A$2:$A$99, 'Revenue Codes'!$B$2:$B$99, "") -> VAT | D34: 9263091587 | E34: 8658405592 | F34: 10861520571 | G34: 10624156667 | H34: 10696166888 | I34: 11243169555 | J34: 1.0141067e+10 | K34: 9.2450921e+09 | L34: 9651623591 | M34: 10335028410 | N34: 10380248034 | O34: 1.1623553e+10 | P34: =SUM(D34:O34) -> 1.2272312e+11
A35: 2021 | B35: 1002.05.00 | C35: =_xlfn.XLOOKUP(B35, 'Revenue Codes'!$A$2:$A$99, 'Revenue Codes'!$B$2:$B$99, "") -> Excise (Spec. Prov.) Levy | P35: =SUM(D35:O35) -> 0
A36: 2021 | B36: 1002.05.01 | C36: =_xlfn.XLOOKUP(B36, 'Revenue Codes'!$A$2:$A$99, 'Revenue Codes'!$B$2:$B$99, "") -> Cigarette | D36: 3762950740 | E36: 6743799800 | F36: 7886301200 | G36: 9208929100 | H36: 9295915800 | I36: 5555444600 | J36: 5233077300 | K36: 7509640000 | L36: 7105069400 | M36: 6767520400 | N36: 12406569100 | O36: 7063623648 | P36: =SUM(D36:O36) -> 88538841088
A37: 2021 | B37: 1002.05.02 | C37: =_xlfn.XLOOKUP(B37, 'Revenue Codes'!$A$2:$A$99, 'Revenue Codes'!$B$2:$B$99, "") -> Liquor | O37: - | P37: =SUM(D37:O37) -> 0
A38: 2021 | B38: 1002.05.03 | C38: =_xlfn.XLOOKUP(B38, 'Revenue Codes'!$A$2:$A$99, 'Revenue Codes'!$B$2:$B$99, "") -> Petroleum Products | D38: 1389275895 | E38: 5788965619 | F38: 7902980851 | G38: 5571406988 | H38: 5636228905 | I38: 1.153928e+09 | J38: 3.309034e+09 | K38: 6.7340692e+09 | L38: 2.1303742e+09 | M38: 4.4388389e+09 | N38: 5.8027016e+09 | O38: 5.4813486e+09 | P38: =SUM(D38:O38) -> 5.5339153e+10
A39: 2021 | B39: 1002.05.04 | C39: =_xlfn.XLOOKUP(B39, 'Revenue Codes'!$A$2:$A$99, 'Revenue Codes'!$B$2:$B$99, "") -> Motor Vehicles | D39: 4984488863 | E39: 1816381558 | F39: 1029316874 | G39: 90823666 | H39: 586936467 | I39: 2052451929 | J39: 524886543 | K39: 499525573 | L39: 1640593021 | M39: 615333668 | N39: 662911331 | O39: 3609033687 | P39: =SUM(D39:O39) -> 18112683180
A40: 2021 | B40: 1002.05.99 | C40: =_xlfn.XLOOKUP(B40, 'Revenue Codes'!$A$2:$A$99, 'Revenue Codes'!$B$2:$B$99, "") -> Excise (Other) | D40: 519728232 | E40: 580557990 | F40: 397187965 | G40: 1167300906 | H40: 342164159 | I40: 258238845 | J40: 7.8627411e+08 | K40: 465725514 | L40: 46483920 | M40: 1.1787554e+09 | N40: 191590101 | O40: 2.995887e+08 | P40: =SUM(D40:O40) -> 6.2335959e+09
A41: 2021 | B41: 1002.12.03 | C41: =_xlfn.XLOOKUP(B41, 'Revenue Codes'!$A$2:$A$99, 'Revenue Codes'!$B$2:$B$99, "") -> NBT | D41: 5360480 | E41: 878066 | F41: 1280460 | G41: 620762 | H41: 539949 | I41: 1831892 | J41: 5950686 | K41: 7212545 | L41: 661063 | M41: 11134499 | N41: 18472112 | O41: 25157883 | P41: =SUM(D41:O41) -> 79100397
A42: 2021 | B42: 1003.06.00 | C42: =_xlfn.XLOOKUP(B42, 'Revenue Codes'!$A$2:$A$99, 'Revenue Codes'!$B$2:$B$99, "") -> ECL | D42: 49236 | I42: 500000 | K42: - | M42: 500000 | O42: -1049236 | P42: =SUM(D42:O42) -> 0
A43: 2021 | B43: 1003.07.10 | C43: =_xlfn.XLOOKUP(B43, 'Revenue Codes'!$A$2:$A$99, 'Revenue Codes'!$B$2:$B$99, "") -> VEL | D43: 5867000 | E43: 4387900 | F43: 5979210 | G43: 5177450 | H43: 7381000 | I43: 9164450 | J43: 7242000 | K43: 4071000 | L43: 10166882 | M43: 8816800 | N43: 3038550 | O43: 4411007 | P43: =SUM(D43:O43) -> 75703249
A44: 2021 | B44: 1004.04.02 | C44: =_xlfn.XLOOKUP(B44, 'Revenue Codes'!$A$2:$A$99, 'Revenue Codes'!$B$2:$B$99, "") -> ESC | D44: - | E44: 295111 | F44: - | G44: 2563704 | H44: 459997 | I44: 1258412 | J44: 7311020 | K44: 12016748 | L44: 4225117 | M44: 8597427 | N44: 3675228 | O44: 2290251 | P44: =SUM(D44:O44) -> 42693015
A45: 2021 | B45: 2003.02.17 | C45: =_xlfn.XLOOKUP(B45, 'Revenue Codes'!$A$2:$A$99, 'Revenue Codes'!$B$2:$B$99, "") -> Sales of Garment | D45: 6265463 | E45: 9937957 | F45: 36755607 | G45: 11188235 | H45: 9754808 | I45: 8937774.9 | J45: 5323553 | K45: 3396992 | L45: 2675325 | M45: 13653725 | N45: 27122320 | O45: 9669826 | P45: =SUM(D45:O45) -> 1.4468159e+08
A46: 2021 | B46: 2003.03.01 | C46: =_xlfn.XLOOKUP(B46, 'Revenue Codes'!$A$2:$A$99, 'Revenue Codes'!$B$2:$B$99, "") -> Fine & Forfeits | D46: 58122612 | E46: 24513603 | F46: 99856111 | G46: 84444328 | H46: 38077395 | I46: 82362190 | J46: 1.8263204e+08 | K46: 1.0090347e+08 | L46: 93749802 | M46: 2.8370255e+09 | N46: 2.0844163e+08 | O46: 2.8115826e+08 | P46: =SUM(D46:O46) -> 4.0912869e+09
A47: 2021 | B47: 2003.02.99 | C47: =_xlfn.XLOOKUP(B47, 'Revenue Codes'!$A$2:$A$99, 'Revenue Codes'!$B$2:$B$99, "") -> Sundris & Others | D47: 7470622 | E47: 22112973 | F47: 17494065 | G47: 13730961 | H47: 25877894 | I47: 32493381 | J47: 27025441 | K47: 19756821 | L47: 20852093 | M47: 18407806 | N47: 22196276 | O47: 25618725 | P47: =SUM(D47:O47) -> 2.5303706e+08
A48: 2021 | B48: 2003.99.00 | C48: =_xlfn.XLOOKUP(B48, 'Revenue Codes'!$A$2:$A$99, 'Revenue Codes'!$B$2:$B$99, "") -> Other Receipts | D48: 10260279 | E48: 10083640 | F48: 15756000 | G48: 13703648 | H48: 11476970 | I48: 12683365 | J48: -5790091178 | K48: 38998188 | L48: 14223123 | M48: 5818529791 | N48: 10800057 | O48: 14246018 | P48: =SUM(D48:O48) -> 1.806699e+08
A49: 2022 | B49: 1001.01.00 | C49: =_xlfn.XLOOKUP(B49, 'Revenue Codes'!$A$2:$A$99, 'Revenue Codes'!$B$2:$B$99, "") -> Import Duty | D49: 3.3571817e+09 | E49: 4.7944928e+09 | F49: 4.8372008e+09 | G49: 4.5165151e+09 | H49: 4.4809179e+09 | I49: 3.1343779e+09 | J49: 3.0531587e+09 | K49: 3.3732566e+09 | L49: 3.4114363e+09 | M49: 3781809224 | N49: 4.1013886e+09 | O49: 3.8206672e+09 | P49: =SUM(D49:O49) -> 4.6662403e+10
A50: 2022 | B50: 1001.01.01 | C50: =_xlfn.XLOOKUP(B50, 'Revenue Codes'!$A$2:$A$99, 'Revenue Codes'!$B$2:$B$99, "") -> Surcharge (Import) | I50: 320462185 | J50: 388864207 | K50: 499176482 | L50: 419648498 | M50: 454188728 | N50: 678154465 | O50: 586543895 | P50: =SUM(D50:O50) -> 3347038460
A51: 2022 | B51: 1001.02.00 | C51: =_xlfn.XLOOKUP(B51, 'Revenue Codes'!$A$2:$A$99, 'Revenue Codes'!$B$2:$B$99, "") -> Export Duty | D51: 1133608 | E51: 1696628 | F51: 1563839 | G51: 585373 | H51: 1812126 | I51: 3709545 | J51: 20373932 | K51: 4111356 | L51: 2315517 | M51: 1001619 | N51: 1464022 | O51: 1551296 | P51: =SUM(D51:O51) -> 41318861
A52: 2022 | B52: 1001.04.00 | C52: =_xlfn.XLOOKUP(B52, 'Revenue Codes'!$A$2:$A$99, 'Revenue Codes'!$B$2:$B$99, "") -> PAL | D52: 11922966955 | E52: 14014910944 | F52: 17557659730 | G52: 19137188056 | H52: 17969416283 | I52: 1.3401247e+10 | J52: 1.3457607e+10 | K52: 1.5379618e+10 | L52: 12593017606 | M52: 13624463639 | N52: 17287247128 | O52: 14250081450 | P52: =SUM(D52:O52) -> 1.8059542e+11
A53: 2022 | B53: 1001.05.00 | C53: =_xlfn.XLOOKUP(B53, 'Revenue Codes'!$A$2:$A$99, 'Revenue Codes'!$B$2:$B$99, "") -> Cess Levy | D53: 1326478 | E53: 21084 | F53: -149169 | G53: 366900 | H53: 167500 | M53: 74361 | O53: -1807154 | P53: =SUM(D53:O53) -> 0
A54: 2022 | B54: 1001.05.01 | C54: =_xlfn.XLOOKUP(B54, 'Revenue Codes'!$A$2:$A$99, 'Revenue Codes'!$B$2:$B$99, "") -> Cess (Import) | D54: 3203690 | E54: 6991562039 | F54: 15053975331 | G54: 6486788609 | H54: 4582176117 | I54: 4.7104546e+09 | J54: 3.9737211e+09 | K54: 4.7675322e+09 | L54: 4462805094 | M54: 5084861984 | N54: 5963884404 | O54: 5994102155 | P54: =SUM(D54:O54) -> 6.8075067e+10
A55: 2022 | B55: 1001.05.02 | C55: =_xlfn.XLOOKUP(B55, 'Revenue Codes'!$A$2:$A$99, 'Revenue Codes'!$B$2:$B$99, "") -> Cess (Export) | D55: 170128220 | E55: 199907129 | F55: 186589506 | G55: 143298171 | H55: 226107405 | I55: 189142155 | J55: 161127204 | K55: 202537109 | L55: 240408262 | M55: 203617216 | N55: 162790214 | O55: 156902493 | P55: =SUM(D55:O55) -> 2242555084
A56: 2022 | B56: 1001.06.00 | C56: =_xlfn.XLOOKUP(B56, 'Revenue Codes'!$A$2:$A$99, 'Revenue Codes'!$B$2:$B$99, "") -> Motor Vehicle (Conc.) Levy | E56: 74486 | K56: -74486 | P56: =SUM(D56:O56) -> 0
A57: 2022 | B57: 1001.08.00 | C57: =_xlfn.XLOOKUP(B57, 'Revenue Codes'!$A$2:$A$99, 'Revenue Codes'!$B$2:$B$99, "") -> SCL | D57: 4251660735 | E57: 3348506009 | F57: 5148969141 | G57: 3047537613 | H57: 2138202445 | I57: 2418760819 | J57: 2254892259 | K57: 2.9148286e+09 | L57: 3708371453 | M57: 3823243664 | N57: 3633255415 | O57: 3505510980 | P57: =SUM(D57:O57) -> 4.0193739e+10
A58: 2022 | B58: 1003.01.00 | C58: =_xlfn.XLOOKUP(B58, 'Revenue Codes'!$A$2:$A$99, 'Revenue Codes'!$B$2:$B$99, "") -> LXT | D58: - | E58: - | F58: 36072111 | G58: - | H58: 20993387 | I58: 178542802 | J58: 0 | K58: 131128769 | L58: 63093249 | M58: 8163330 | N58: 17582787 | O58: 411845284 | P58: =SUM(D58:O58) -> 867421719
A59: 2022 | B59: 1002.01.04 | C59: =_xlfn.XLOOKUP(B59, 'Revenue Codes'!$A$2:$A$99, 'Revenue Codes'!$B$2:$B$99, "") -> VAT | D59: 11579443378 | E59: 11564228149 | F59: 14160090415 | G59: 13635575282 | H59: 11283314742 | I59: 14227881264 | J59: 1.2710794e+10 | K59: 1.3755652e+10 | L59: 14025522104 | M59: 17593941322 | N59: 18658532462 | O59: 17694802907 | P59: =SUM(D59:O59) -> 1.7088978e+11
A60: 2022 | B60: 1002.05.00 | C60: =_xlfn.XLOOKUP(B60, 'Revenue Codes'!$A$2:$A$99, 'Revenue Codes'!$B$2:$B$99, "") -> Excise (Spec. Prov.) Levy | P60: =SUM(D60:O60) -> 0
A61: 2022 | B61: 1002.05.01 | C61: =_xlfn.XLOOKUP(B61, 'Revenue Codes'!$A$2:$A$99, 'Revenue Codes'!$B$2:$B$99, "") -> Cigarette | D61: 13711591188 | E61: 6636233927 | F61: 4714438546 | G61: 7900000000 | H61: 8737432832 | J61: 19670036100 | K61: 8824681890 | L61: 12435814600 | M61: 5705179000 | N61: 6545398923 | O61: 9279254900 | P61: =SUM(D61:O61) -> 104160061906
A62: 2022 | B62: 1002.05.02 | C62: =_xlfn.XLOOKUP(B62, 'Revenue Codes'!$A$2:$A$99, 'Revenue Codes'!$B$2:$B$99, "") -> Liquor | P62: =SUM(D62:O62) -> 0
A63: 2022 | B63: 1002.05.03 | C63: =_xlfn.XLOOKUP(B63, 'Revenue Codes'!$A$2:$A$99, 'Revenue Codes'!$B$2:$B$99, "") -> Petroleum Products | D63: 3478669708 | E63: 5012150056 | F63: 1100253168 | G63: 6854963822 | H63: 7144789798 | I63: 2.9184484e+09 | J63: 6.0778029e+09 | K63: 2.7471145e+09 | L63: 1330601475 | M63: 4578596517 | N63: 3.4784325e+09 | O63: 8351711316 | P63: =SUM(D63:O63) -> 5.3073534e+10
A64: 2022 | B64: 1002.05.04 | C64: =_xlfn.XLOOKUP(B64, 'Revenue Codes'!$A$2:$A$99, 'Revenue Codes'!$B$2:$B$99, "") -> Motor Vehicles | D64: 1273416475 | E64: 2453102705 | F64: 6938569404 | G64: 459464330 | H64: 434787492 | I64: 570865630 | J64: 375019903 | K64: 1016340024 | L64: 150320848 | M64: 223500498 | N64: 249534127 | O64: 358660643 | P64: =SUM(D64:O64) -> 14503582079
A65: 2022 | B65: 1002.05.99 | C65: =_xlfn.XLOOKUP(B65, 'Revenue Codes'!$A$2:$A$99, 'Revenue Codes'!$B$2:$B$99, "") -> Excise (Other) | D65: 710986943 | E65: 276558232 | F65: 489583934 | G65: 814019479 | H65: 537349814 | I65: 399569001 | J65: 5.3675112e+08 | K65: 5.9682141e+08 | L65: 215852793 | M65: 782177649 | N65: 119485973 | O65: 119257142 | P65: =SUM(D65:O65) -> 5.5984135e+09
A66: 2022 | B66: 1002.12.03 | C66: =_xlfn.XLOOKUP(B66, 'Revenue Codes'!$A$2:$A$99, 'Revenue Codes'!$B$2:$B$99, "") -> NBT | D66: 646311 | E66: 1557566 | F66: 441975 | G66: 10748230 | H66: 931028 | I66: 16071680 | J66: 341071 | K66: 171500 | L66: 3987032 | M66: 12646482 | N66: 1354619 | O66: 5651337 | P66: =SUM(D66:O66) -> 54548831
A67: 2022 | B67: 1002.16.00 | C67: =_xlfn.XLOOKUP(B67, 'Revenue Codes'!$A$2:$A$99, 'Revenue Codes'!$B$2:$B$99, "") -> SSCL | M67: 3488216361 | N67: 4681472307 | O67: 4499520547 | P67: =SUM(D67:O67) -> 12669209215
A68: 2022 | B68: 1003.06.00 | C68: =_xlfn.XLOOKUP(B68, 'Revenue Codes'!$A$2:$A$99, 'Revenue Codes'!$B$2:$B$99, "") -> ECL | P68: =SUM(D68:O68) -> 0
A69: 2022 | B69: 1003.07.10 | C69: =_xlfn.XLOOKUP(B69, 'Revenue Codes'!$A$2:$A$99, 'Revenue Codes'!$B$2:$B$99, "") -> VEL | D69: 64388475 | E69: 9496346 | F69: 1918350 | G69: 2013210 | H69: 638270 | I69: 872274 | J69: 613000 | K69: 924500 | L69: 937500 | M69: 11588000 | N69: 7607886 | O69: 7006991 | P69: =SUM(D69:O69) -> 108004802
A70: 2022 | B70: 1004.04.02 | C70: =_xlfn.XLOOKUP(B70, 'Revenue Codes'!$A$2:$A$99, 'Revenue Codes'!$B$2:$B$99, "") -> ESC | D70: 20812212 | E70: 3666490 | F70: 1038473 | G70: 475318 | H70: 14357 | I70: 988112 | J70: 20551 | K70: 239702 | L70: 112877 | M70: 354590 | P70: =SUM(D70:O70) -> 27722682
A71: 2022 | B71: 2003.02.17 | C71: =_xlfn.XLOOKUP(B71, 'Revenue Codes'!$A$2:$A$99, 'Revenue Codes'!$B$2:$B$99, "") -> Sales of Garment | D71: 11419777 | E71: 36987775 | F71: 19445298 | G71: 7414617 | H71: 9268859 | I71: 8874825 | J71: 12648250 | K71: 13326800 | L71: 15825025 | M71: 20778200 | N71: 21454431 | O71: 18756533 | P71: =SUM(D71:O71) -> 196200390
A72: 2022 | B72: 2003.03.01 | C72: =_xlfn.XLOOKUP(B72, 'Revenue Codes'!$A$2:$A$99, 'Revenue Codes'!$B$2:$B$99, "") -> Fine & Forfeits | D72: 73974850 | E72: 43847736 | F72: 154178061 | G72: 283330028 | H72: 188966658 | I72: 86752317 | J72: 7.4076845e+08 | K72: 2.784549e+08 | L72: 40948141 | M72: 2345629012 | N72: 174532075 | O72: 137759414 | P72: =SUM(D72:O72) -> 4.5491416e+09
A73: 2022 | B73: 2003.02.99 | C73: =_xlfn.XLOOKUP(B73, 'Revenue Codes'!$A$2:$A$99, 'Revenue Codes'!$B$2:$B$99, "") -> Sundris & Others | D73: 15186219 | E73: 21696871 | F73: 34407868 | G73: 19655059 | H73: 16446169 | I73: 20037437 | J73: 17279871 | K73: 18759532 | L73: 19945216 | M73: 19311521 | N73: 20164854 | O73: 20192352 | P73: =SUM(D73:O73) -> 2.4308297e+08
A74: 2022 | B74: 2003.99.00 | C74: =_xlfn.XLOOKUP(B74, 'Revenue Codes'!$A$2:$A$99, 'Revenue Codes'!$B$2:$B$99, "") -> Other Receipts | D74: 124206857 | E74: 1941376 | F74: 18376742 | G74: 14656435 | H74: 10874018 | I74: 20919888 | J74: 15221210 | K74: 20378577 | L74: 20023269 | M74: 19629136 | N74: 17009805 | O74: 24434861 | P74: =SUM(D74:O74) -> 3.0767217e+08
A75: 2023 | B75: 1001.01.00 | C75: =_xlfn.XLOOKUP(B75, 'Revenue Codes'!$A$2:$A$99, 'Revenue Codes'!$B$2:$B$99, "") -> Import Duty | D75: 5.7733993e+09 | E75: 5.2882309e+09 | F75: 4.1951805e+09 | G75: 5.0070172e+09 | H75: 5.5016301e+09 | I75: 6.0953726e+09 | J75: 7.7686107e+09 | K75: 2.3957857e+10 | L75: 2512205887 | M75: 1.086587e+10 | N75: 1.8031933e+10 | O75: 1.0123041e+10 | P75: =SUM(D75:O75) -> 1.0512035e+11
A76: 2023 | B76: 1001.02.00 | C76: =_xlfn.XLOOKUP(B76, 'Revenue Codes'!$A$2:$A$99, 'Revenue Codes'!$B$2:$B$99, "") -> Export Duty | D76: 1294230 | E76: 1414201 | F76: 2404853.5 | G76: 2469854 | H76: 2674440 | I76: 2511689 | J76: 22607799 | K76: 2691658 | L76: -17630559 | M76: 2725468 | N76: 2460323 | O76: 1126398 | P76: =SUM(D76:O76) -> 26750354
A77: 2023 | B77: 1001.04.00 | C77: =_xlfn.XLOOKUP(B77, 'Revenue Codes'!$A$2:$A$99, 'Revenue Codes'!$B$2:$B$99, "") -> PAL | D77: 1.3885272e+10 | E77: 2.0081148e+10 | F77: 1.214984e+10 | G77: 1.0569125e+10 | H77: 1.1860096e+10 | I77: 1.2066149e+10 | J77: 1.3029408e+10 | K77: 1.6540957e+10 | L77: 1.3442963e+10 | M77: 1.9303454e+10 | N77: 1.750151e+10 | O77: 1.5056416e+10 | P77: =SUM(D77:O77) -> 1.7548634e+11
A78: 2023 | B78: 1001.05.01 | C78: =_xlfn.XLOOKUP(B78, 'Revenue Codes'!$A$2:$A$99, 'Revenue Codes'!$B$2:$B$99, "") -> Cess (Import) | D78: 6.762414e+09 | E78: 4.8711305e+09 | F78: 5.1956373e+09 | G78: -8.6986467e+08 | H78: 3.6879257e+09 | I78: 3.9553356e+09 | J78: 4.2899232e+09 | K78: 5.3139742e+09 | L78: 4580939526 | M78: 5501315857 | N78: 5960818902 | O78: 5.7060559e+09 | P78: =SUM(D78:O78) -> 5.4955606e+10
A79: 2023 | B79: 1001.05.02 | C79: =_xlfn.XLOOKUP(B79, 'Revenue Codes'!$A$2:$A$99, 'Revenue Codes'!$B$2:$B$99, "") -> Cess (Export) | D79: 166136346 | E79: 244734461 | F79: 169592937 | G79: 123460993 | H79: 176082675 | I79: 187604018 | J79: 1.6347713e+08 | K79: 299600141 | L79: 202618834 | M79: 167738375 | N79: 169440048 | O79: 158019745 | P79: =SUM(D79:O79) -> 2.2285057e+09
A80: 2023 | B80: 1001.08.00 | C80: =_xlfn.XLOOKUP(B80, 'Revenue Codes'!$A$2:$A$99, 'Revenue Codes'!$B$2:$B$99, "") -> SCL | D80: 3188576571 | E80: 3164823383 | F80: 4.9443296e+09 | G80: 3574073462 | H80: 6045944417 | I80: 4791440344 | J80: 5.6063058e+09 | K80: 682574668 | L80: 4785353391 | M80: 6944167067 | N80: 455158827 | O80: 7144705365 | P80: =SUM(D80:O80) -> 5.1327453e+10
A81: 2023 | B81: 1002.05.01 | C81: =_xlfn.XLOOKUP(B81, 'Revenue Codes'!$A$2:$A$99, 'Revenue Codes'!$B$2:$B$99, "") -> Cigarette | D81: 8969009838 | E81: 10145283482 | F81: 13310135906 | G81: 10281697694 | H81: 10353568120 | I81: 9532142125 | J81: 11401254253 | K81: 2400 | L81: 1.5454876e+10 | M81: 8941166775 | N81: 9475808140 | O81: 9601757181 | P81: =SUM(D81:O81) -> 1.174667e+11
A82: 2023 | B82: 1002.05.03 | C82: =_xlfn.XLOOKUP(B82, 'Revenue Codes'!$A$2:$A$99, 'Revenue Codes'!$B$2:$B$99, "") -> Petroleum Products | D82: 1.0547862e+10 | E82: 8.6601119e+09 | F82: 5.3797617e+09 | G82: 3.1714495e+09 | H82: 1.7828971e+09 | I82: 2.6978519e+09 | J82: 1.0036307e+10 | K82: 1.6399968e+10 | L82: 1.3577742e+10 | M82: 3.4083613e+10 | N82: 1.7234633e+10 | O82: 2.0070242e+10 | P82: =SUM(D82:O82) -> 1.4364244e+11
... A101: 2024 | B101: 1002.05.01 | C101: =_xlfn.XLOOKUP(B101, 'Revenue Codes'!$A$2:$A$99, 'Revenue Codes'!$B$2:$B$99, "") -> Cigarette | D101: 10820000000 | E101: 5861000000 | F101: 8362000000 | G101: 9556000000 | H101: 10105000000 | I101: 8378000000 | J101: 14743000000 | K101: 3062000000 | L101: 7974000000 | M101: 9261000000 | N101: 9126000000 | O101: 19896000000 | P101: =SUM(D101:O101) -> 117144000000
A102: 2024 | B102: 1002.05.02 | C102: =_xlfn.XLOOKUP(B102, 'Revenue Codes'!$A$2:$A$99, 'Revenue Codes'!$B$2:$B$99, "") -> Liquor | D102: - | E102: - | F102: - | G102: - | H102: - | I102: - | J102: - | K102: - | L102: - | M102: - | N102: - | O102: - | P102: =SUM(D102:O102) -> 0
A103: 2024 | B103: 1002.05.03 | C103: =_xlfn.XLOOKUP(B103, 'Revenue Codes'!$A$2:$A$99, 'Revenue Codes'!$B$2:$B$99, "") -> Petroleum Products | D103: 26335550000 | E103: 13398000000 | F103: 16541000000 | G103: 17485000000 | H103: 12336000000 | I103: 7743000000 | J103: 23337000000 | K103: 22123000000 | L103: 21291000000 | M103: 15550000000 | N103: 9478000000 | O103: 14583000000 | P103: =SUM(D103:O103) -> 200200550000
A104: 2024 | B104: 1002.05.04 | C104: =_xlfn.XLOOKUP(B104, 'Revenue Codes'!$A$2:$A$99, 'Revenue Codes'!$B$2:$B$99, "") -> Motor Vehicles | D104: 672000000 | E104: 2916000000 | F104: 4259000000 | G104: 9316000000 | H104: 11021000000 | I104: 1315000000 | J104: 1198000000 | K104: 5836000000 | L104: 5009000000 | M104: 6001000000 | N104: 7063000000 | O104: 3957000000 | P104: =SUM(D104:O104) -> 58563000000
A105: 2024 | B105: 1002.05.99 | C105: =_xlfn.XLOOKUP(B105, 'Revenue Codes'!$A$2:$A$99, 'Revenue Codes'!$B$2:$B$99, "") -> Excise (Other) | D105: 592000000 | E105: 406000000 | F105: 281000000 | G105: 948000000 | H105: 342000000 | I105: 388000000 | J105: 1034000000 | K105: 698000000 | L105: 466000000 | M105: 1259000000 | N105: 990000000 | O105: 636000000 | P105: =SUM(D105:O105) -> 8040000000
A106: 2024 | B106: 1003.07.10 | C106: =_xlfn.XLOOKUP(B106, 'Revenue Codes'!$A$2:$A$99, 'Revenue Codes'!$B$2:$B$99, "") -> VEL | D106: 6000000 | E106: 11000000 | F106: 12000000 | G106: 8000000 | H106: 12000000 | I106: 13000000 | J106: 69000000 | K106: 19000000 | L106: 23000000 | M106: 22000000 | N106: 24000000 | O106: 23000000 | P106: =SUM(D106:O106) -> 242000000
A107: 2024 | B107: 2003.02.17 | C107: =_xlfn.XLOOKUP(B107, 'Revenue Codes'!$A$2:$A$99, 'Revenue Codes'!$B$2:$B$99, "") -> Sales of Garment | D107: 26000000 | E107: 7000000 | F107: 9000000 | G107: 8000000 | H107: 7000000 | I107: 10000000 | J107: 7000000 | K107: 7000000 | L107: 7000000 | M107: 8000000 | N107: 15000000 | O107: 12000000 | P107: =SUM(D107:O107) -> 123000000
A108: 2024 | B108: 2003.03.01 | C108: =_xlfn.XLOOKUP(B108, 'Revenue Codes'!$A$2:$A$99, 'Revenue Codes'!$B$2:$B$99, "") -> Fine & Forfeits | D108: 271000000 | E108: 402000000 | F108: 227000000 | G108: 278000000 | H108: 810000000 | I108: 828000000 | J108: 552000000 | K108: 277000000 | L108: 396000000 | M108: 216000000 | N108: 673000000 | O108: 3092000000 | P108: =SUM(D108:O108) -> 8022000000
A109: 2024 | B109: 1004.04.02 | C109: =_xlfn.XLOOKUP(B109, 'Revenue Codes'!$A$2:$A$99, 'Revenue Codes'!$B$2:$B$99, "") -> ESC | D109: - | E109: 3000000 | F109: 196000000 | G109: - | H109: 2000000 | I109: 1000000 | J109: - | K109: 88000 | L109: - | M109: 1000000 | N109: - | O109: 47000 | P109: =SUM(D109:O109) -> 203135000
A110: 2024 | B110: 1002.12.03 | C110: =_xlfn.XLOOKUP(B110, 'Revenue Codes'!$A$2:$A$99, 'Revenue Codes'!$B$2:$B$99, "") -> NBT | D110: 1000000 | E110: 2000000 | F110: - | G110: - | H110: - | I110: - | J110: - | K110: 248000 | L110: 1000000 | M110: - | N110: - | O110: 3000000 | P110: =SUM(D110:O110) -> 7248000
A111: 2024 | B111: 1002.01.04 | C111: =_xlfn.XLOOKUP(B111, 'Revenue Codes'!$A$2:$A$99, 'Revenue Codes'!$B$2:$B$99, "") -> VAT | D111: 42308000000 | E111: 46760000000 | F111: 42665000000 | G111: 48981000000 | H111: 45478000000 | I111: 28369000000 | J111: 60613000000 | K111: 58935000000 | L111: 62020000000 | M111: 55489000000 | N111: 48460000000 | O111: 57415000000 | P111: =SUM(D111:O111) -> 597493000000
A112: 2024 | B112: 1002.16.00 | C112: =_xlfn.XLOOKUP(B112, 'Revenue Codes'!$A$2:$A$99, 'Revenue Codes'!$B$2:$B$99, "") -> SSCL | D112: 5234000000 | E112: 5365450000 | F112: 4861000000 | G112: 4610000000 | H112: 4397000000 | I112: 3643000000 | J112: 7084000000 | K112: 5727000000 | L112: 5687000000 | M112: 5810000000 | N112: 5186000000 | O112: 6789000000 | P112: =SUM(D112:O112) -> 64393450000
A113: 2024 | B113: 1003.01.00 | C113: =_xlfn.XLOOKUP(B113, 'Revenue Codes'!$A$2:$A$99, 'Revenue Codes'!$B$2:$B$99, "") -> LXT | D113: 147000000 | E113: 148000000 | F113: 206000000 | G113: 62000000 | H113: 178000000 | I113: 195000000 | J113: 201000000 | K113: 507000000 | L113: 288000000 | M113: 347000000 | N113: 223000000 | O113: 269000000 | P113: =SUM(D113:O113) -> 2771000000
A114: 2024 | B114: 2003.02.99 | C114: =_xlfn.XLOOKUP(B114, 'Revenue Codes'!$A$2:$A$99, 'Revenue Codes'!$B$2:$B$99, "") -> Sundris & Others | D114: 23000000 | E114: 16000000 | F114: 29000000 | G114: 23000000 | H114: 28000000 | I114: 22000000 | J114: 26000000 | K114: 26000000 | L114: 28000000 | M114: 24000000 | N114: 25000000 | O114: 28000000 | P114: =SUM(D114:O114) -> 298000000
A115: 2024 | B115: 2003.99.00 | C115: =_xlfn.XLOOKUP(B115, 'Revenue Codes'!$A$2:$A$99, 'Revenue Codes'!$B$2:$B$99, "") -> Other Receipts | D115: 12000000 | E115: 19000000 | F115: 8000000 | G115: 10000000 | H115: 14000000 | I115: 4000000 | J115: 11000000 | K115: 8000000 | L115: 11000000 | M115: 9000000 | N115: 5000000 | O115: 11249000 | P115: =SUM(D115:O115) -> 122249000
A116: 2025 | B116: 1001.01.00 | C116: =_xlfn.XLOOKUP(B116, 'Revenue Codes'!$A$2:$A$99, 'Revenue Codes'!$B$2:$B$99, "") -> Import Duty | D116: 9576938116 | E116: 1.0765595e+10 | F116: 1.5173255e+10 | G116: 2.1022418e+10 | H116: 1.6718344e+10 | I116: 20695898665 | J116: 27996372948 | K116: 2.9039626e+10 | L116: 28044876718 | M116: 31036526520 | N116: 3.080301e+10 | O116: 3.2768204e+10 | P116: =SUM(D116:O116) -> 2.7364107e+11
A117: 2025 | B117: 1001.02.00 | C117: =_xlfn.XLOOKUP(B117, 'Revenue Codes'!$A$2:$A$99, 'Revenue Codes'!$B$2:$B$99, "") -> Export Duty | D117: 2118022 | E117: 2340839 | F117: 180696330 | G117: -174493246 | H117: 4133736 | I117: 928637 | J117: 231030 | K117: 552556 | L117: 466379 | M117: 614279 | N117: 484702 | O117: 114458 | P117: =SUM(D117:O117) -> 18187722
A118: 2025 | B118: 1001.04.00 | C118: =_xlfn.XLOOKUP(B118, 'Revenue Codes'!$A$2:$A$99, 'Revenue Codes'!$B$2:$B$99, "") -> PAL | D118: 12895322674 | E118: 1.3030549e+10 | F118: 1.6123101e+10 | G118: 1.3695749e+10 | H118: 1.6769477e+10 | I118: 1.2917037e+10 | J118: 1.5273397e+10 | K118: 1.5181775e+10 | L118: 14303021083 | M118: 1.6692103e+10 | N118: 1.4167471e+10 | O118: 14414041 | P118: =SUM(D118:O118) -> 1.6106342e+11
...

Sheet Estimated Revenue
A1: Year | B1: Revenue Code | C1: Description | D1: January | E1: February | F1: March | G1: April | H1: May | I1: June | J1: July | K1: August | L1: September | M1: October | N1: November | O1: December | P1: Total | S1: Instructions
A2: 2022 | B2: 1001.01.00 | C2: =_xlfn.XLOOKUP(B2, 'Revenue Codes'!$A$2:$A$99, 'Revenue Codes'!$B$2:$B$99, "") -> Import Duty | D2: 3241000 | E2: 3124000 | F2: 3112000 | G2: 3158000 | H2: 3237000 | I2: 3339000 | J2: 3455000 | K2: 3582000 | L2: 3717000 | M2: 3860000 | N2: 4009000 | O2: 4165000 | P2: 41999000 | S2: 1) Revenue Code description appears automatically when code is entered. If code does not appear, add a new Revenue Code in the relevant Excel Sheet. 2) Fields automatically turns red if negative values are entered. Check and verify if those values are correct. 3) Enter all values in exact figures LKR '000 (Hundred Thousand's). Please maintain this standard 4) Values entered in this shared Excel automatically updates the Revenue Dashboard. If any errors in the dashboard is noticed, check values in this Excel Sheet.
A3: 2022 | B3: 1001.02.00 | C3: =_xlfn.XLOOKUP(B3, 'Revenue Codes'!$A$2:$A$99, 'Revenue Codes'!$B$2:$B$99, "") -> Export Duty | D3: 2000 | E3: 2000 | F3: 3000 | G3: 2000 | H3: 2000 | I3: 3000 | J3: 2000 | K3: 3000 | L3: 2000 | M3: 3000 | N3: 3000 | O3: 4000 | P3: 31000
A4: 2022 | B4: 1001.04.00 | C4: =_xlfn.XLOOKUP(B4, 'Revenue Codes'!$A$2:$A$99, 'Revenue Codes'!$B$2:$B$99, "") -> PAL | D4: 13341000 | E4: 12695000 | F4: 13556000 | G4: 13747000 | H4: 14267000 | I4: 14654000 | J4: 15122000 | K4: 15571000 | L4: 16050000 | M4: 15491000 | N4: 15995000 | O4: 16513000 | P4: 177002000
A5: 2022 | B5: 1001.05.01 | C5: =_xlfn.XLOOKUP(B5, 'Revenue Codes'!$A$2:$A$99, 'Revenue Codes'!$B$2:$B$99, "") -> Cess (Import) | D5: 5421000 | E5: 5330000 | F5: 5575000 | G5: 5173000 | H5: 5105000 | I5: 5892000 | J5: 5756000 | K5: 5633000 | L5: 5522000 | M5: 5421000 | N5: 5529000 | O5: 5643000 | P5: 66000000
A6: 2022 | B6: 1001.05.02 | C6: =_xlfn.XLOOKUP(B6, 'Revenue Codes'!$A$2:$A$99, 'Revenue Codes'!$B$2:$B$99, "") -> Cess (Export) | D6: 162000 | E6: 169000 | F6: 170000 | G6: 169000 | H6: 169000 | I6: 168000 | J6: 167000 | K6: 167000 | L6: 166000 | M6: 165000 | N6: 164000 | O6: 164000 | P6: 2000000
A7: 2022 | B7: 1001.08.00 | C7: =_xlfn.XLOOKUP(B7, 'Revenue Codes'!$A$2:$A$99, 'Revenue Codes'!$B$2:$B$99, "") -> SCL | D7: 2883000 | E7: 2948000 | F7: 2963000 | G7: 2960000 | H7: 2951000 | I7: 2939000 | J7: 2926000 | K7: 2913000 | L7: 2899000 | M7: 2886000 | N7: 2873000 | O7: 2860000 | P7: 35001000
A8: 2022 | B8: 1002.01.04 | C8: =_xlfn.XLOOKUP(B8, 'Revenue Codes'!$A$2:$A$99, 'Revenue Codes'!$B$2:$B$99, "") -> VAT | D8: 16482000 | E8: 15261000 | F8: 16800000 | G8: 16435000 | H8: 17426000 | I8: 17489000 | J8: 18223000 | K8: 18508000 | L8: 19129000 | M8: 19536000 | N8: 20115000 | O8: 20596000 | P8: 216000000
A9: 2022 | B9: 1002.05.01 | C9: =_xlfn.XLOOKUP(B9, 'Revenue Codes'!$A$2:$A$99, 'Revenue Codes'!$B$2:$B$99, "") -> Cigarette | D9: 7567000 | E9: 8834000 | F9: 9068000 | G9: 9150000 | H9: 9212000 | I9: 9272000 | J9: 9331000 | K9: 9392000 | L9: 9452000 | M9: 9513000 | N9: 9574000 | O9: 9636000 | P9: 110001000
A10: 2022 | B10: 1002.05.03 | C10: =_xlfn.XLOOKUP(B10, 'Revenue Codes'!$A$2:$A$99, 'Revenue Codes'!$B$2:$B$99, "") -> Petroleum Products | D10: 2896000 | E10: 5691000 | F10: 5046000 | G10: 5008000 | H10: 4892000 | I10: 4790000 | J10: 4688000 | K10: 4588000 | L10: 4491000 | M10: 4396000 | N10: 4302000 | O10: 4211000 | P10: 54999000
A11: 2022 | B11: 1002.05.04 | C11: =_xlfn.XLOOKUP(B11, 'Revenue Codes'!$A$2:$A$99, 'Revenue Codes'!$B$2:$B$99, "") -> Motor Vehicles | D11: 1480000 | E11: 2319000 | F11: 1061000 | G11: 1480000 | H11: 1110000 | I11: 1529000 | J11: 1258000 | K11: 1283000 | L11: 1334000 | M11: 1568000 | N11: 1727000 | O11: 1850000 | P11: 17999000
A12: 2022 | B12: 1002.05.99 | C12: =_xlfn.XLOOKUP(B12, 'Revenue Codes'!$A$2:$A$99, 'Revenue Codes'!$B$2:$B$99, "") -> Excise (Other) | D12: 491000 | E12: 491000 | F12: 491000 | G12: 491000 | H12: 491000 | I12: 491000 | J12: 438000 | K12: 511000 | L12: 483000 | M12: 494000 | N12: 490000 | O12: 639000 | P12: 6001000
A13: 2022 | B13: 1003.07.10 | C13: =_xlfn.XLOOKUP(B13, 'Revenue Codes'!$A$2:$A$99, 'Revenue Codes'!$B$2:$B$99, "") -> VEL | D13: 12000 | E13: 11000 | F13: 10000 | G13: 10000 | H13: 9000 | I13: 9000 | J13: 9000 | K13: 8000 | L13: 8000 | M13: 7000 | N13: 7000 | O13: 7000 | P13: 107000
A14: 2022 | B14: 1003.01.00 | C14: =_xlfn.XLOOKUP(B14, 'Revenue Codes'!$A$2:$A$99, 'Revenue Codes'!$B$2:$B$99, "") -> LXT | D14: 49000 | E14: 37000 | F14: 49000 | G14: 37000 | H14: 59000 | I14: 70000 | J14: 86000 | K14: 98000 | L14: 112000 | M14: 132000 | N14: 141000 | O14: 132000 | P14: 1002000
A15: 2022 | B15: 1002.12.03 | C15: =_xlfn.XLOOKUP(B15, 'Revenue Codes'!$A$2:$A$99, 'Revenue Codes'!$B$2:$B$99, "") -> NBT
A16: 2022 | B16: 1002.16.00 | C16: =_xlfn.XLOOKUP(B16, 'Revenue Codes'!$A$2:$A$99, 'Revenue Codes'!$B$2:$B$99, "") -> SSCL | M16: 2500000 | N16: 2500000 | O16: 2500000 | P16: 7500000
A17: 2022 | B17: 1004.04.02 | C17: =_xlfn.XLOOKUP(B17, 'Revenue Codes'!$A$2:$A$99, 'Revenue Codes'!$B$2:$B$99, "") -> ESC
A18: 2022 | B18: 2003.02.17 | C18: =_xlfn.XLOOKUP(B18, 'Revenue Codes'!$A$2:$A$99, 'Revenue Codes'!$B$2:$B$99, "") -> Sales of Garment | D18: 8000 | E18: 13000 | F18: 13000 | G18: 13000 | H18: 13000 | I18: 13000 | J18: 13000 | K18: 13000 | L18: 13000 | M18: 13000 | N18: 13000 | O18: 13000 | P18: 151000
A19: 2022 | B19: 2003.03.01 | C19: =_xlfn.XLOOKUP(B19, 'Revenue Codes'!$A$2:$A$99, 'Revenue Codes'!$B$2:$B$99, "") -> Fine & Forfeits | D19: 82000 | E19: 178000 | F19: 181000 | G19: 178000 | H19: 181000 | I19: 179000 | J19: 180000 | K19: 179000 | L19: 180000 | M19: 179000 | N19: 180000 | O19: 179000 | P19: 2056000
A20: 2022 | B20: 2003.02.99 | C20: =_xlfn.XLOOKUP(B20, 'Revenue Codes'!$A$2:$A$99, 'Revenue Codes'!$B$2:$B$99, "") -> Sundris & Others | D20: 14000 | E20: 14000 | F20: 14000 | G20: 13000 | H20: 13000 | I20: 13000 | J20: 12000 | K20: 12000 | L20: 12000 | M20: 12000 | N20: 11000 | O20: 11000 | P20: 151000
A21: 2022 | B21: 2003.99.00 | C21: =_xlfn.XLOOKUP(B21, 'Revenue Codes'!$A$2:$A$99, 'Revenue Codes'!$B$2:$B$99, "") -> Other Receipts | D21: 15000 | E21: 16000 | F21: 16000 | G21: 16000 | H21: 17000 | I21: 17000 | J21: 17000 | K21: 17000 | L21: 17000 | M21: 17000 | N21: 17000 | O21: 17000 | P21: 199000
A22: 2024 | B22: 1001.01.00 | C22: =_xlfn.XLOOKUP(B22, 'Revenue Codes'!$A$2:$A$99, 'Revenue Codes'!$B$2:$B$99, "") -> Import Duty | D22: 8495000 | E22: 14960000 | F22: 11651000 | G22: 8578000 | H22: 12189000 | I22: 12655000 | J22: 7087000 | K22: 26869000 | L22: 15645000 | M22: 13640000 | N22: 22665000 | O22: 20566000 | P22: 175000000
A23: 2024 | B23: 1001.02.00 | C23: =_xlfn.XLOOKUP(B23, 'Revenue Codes'!$A$2:$A$99, 'Revenue Codes'!$B$2:$B$99, "") -> Export Duty | D23: 1000 | E23: 1000 | F23: 3000 | G23: 3000 | H23: 4000 | I23: 4000 | J23: 3000 | K23: 3000 | L23: 5000 | M23: 3000 | N23: 2000 | O23: 3000 | P23: 35000
A24: 2024 | B24: 1001.04.00 | C24: =_xlfn.XLOOKUP(B24, 'Revenue Codes'!$A$2:$A$99, 'Revenue Codes'!$B$2:$B$99, "") -> PAL | D24: 13731000 | E24: 19891000 | F24: 15831000 | G24: 11831000 | H24: 13407000 | I24: 13823000 | J24: 12918000 | K24: 12062000 | L24: 15045000 | M24: 15531000 | N24: 15902000 | O24: 15027000 | P24: 174999000
A25: 2024 | B25: 1001.05.01 | C25: =_xlfn.XLOOKUP(B25, 'Revenue Codes'!$A$2:$A$99, 'Revenue Codes'!$B$2:$B$99, "") -> Cess (Import) | D25: 7188000 | E25: 6036000 | F25: 3422000 | G25: 4916000 | H25: 6055000 | I25: 6132000 | J25: 5422000 | K25: 2862000 | L25: 6012000 | M25: 2862000 | N25: 3042000 | O25: 4051000 | P25: 58000000
A26: 2024 | B26: 1001.05.02 | C26: =_xlfn.XLOOKUP(B26, 'Revenue Codes'!$A$2:$A$99, 'Revenue Codes'!$B$2:$B$99, "") -> Cess (Export) | D26: 140000 | E26: 207000 | F26: 158000 | G26: 112000 | H26: 169000 | I26: 183000 | J26: 141000 | K26: 220000 | L26: 193000 | M26: 115000 | N26: 130000 | O26: 232000 | P26: 2000000
A27: 2024 | B27: 1001.08.00 | C27: =_xlfn.XLOOKUP(B27, 'Revenue Codes'!$A$2:$A$99, 'Revenue Codes'!$B$2:$B$99, "") -> SCL | D27: 6753000 | E27: 5215000 | F27: 12584000 | G27: 6652000 | H27: 9624000 | I27: 10237000 | J27: 10384000 | K27: 8943000 | L27: 9955000 | M27: 10446000 | N27: 2879000 | O27: 1329000 | P27: 95001000
A28: 2024 | B28: 1002.01.04 | C28: =_xlfn.XLOOKUP(B28, 'Revenue Codes'!$A$2:$A$99, 'Revenue Codes'!$B$2:$B$99, "") -> VAT | D28: 51795000 | E28: 45687000 | F28: 50758000 | G28: 44964000 | H28: 54219000 | I28: 51833000 | J28: 59099000 | K28: 56181000 | L28: 56431000 | M28: 59957000 | N28: 66244000 | O28: 62833000 | P28: 660001000
A29: 2024 | B29: 1002.16.03 | C29: =_xlfn.XLOOKUP(B29, 'Revenue Codes'!$A$2:$A$99, 'Revenue Codes'!$B$2:$B$99, "") -> SSL | D29: 5004000 | E29: 3835000 | F29: 4080000 | G29: 4036000 | H29: 6153000 | I29: 5852000 | J29: 4593000 | K29: 3790000 | L29: 4867000 | M29: 4486000 | N29: 4281000 | O29: 4023000 | P29: 55000000
... A41: 2024 | B41: 2003.99.00 | C41: =_xlfn.XLOOKUP(B41, 'Revenue Codes'!$A$2:$A$99, 'Revenue Codes'!$B$2:$B$99, "") -> Other Receipts | D41: 18000 | E41: 17000 | F41: 18000 | G41: 17000 | H41: 17000 | I41: 18000 | J41: 17000 | K41: 18000 | L41: 17000 | M41: 18000 | N41: 17000 | O41: 18000 | P41: 210000
A42: 2025 | B42: 1001.01.00 | C42: =_xlfn.XLOOKUP(B42, 'Revenue Codes'!$A$2:$A$99, 'Revenue Codes'!$B$2:$B$99, "") -> Import Duty | D42: 9577000 | E42: 10766000 | F42: 11611000 | G42: 17294953 | H42: 21925625 | I42: 22534924 | J42: 23753522 | K42: 23144223 | L42: 22534924 | M42: 24972120 | N42: 25581418 | O42: 26304292 | P42: =SUM(D42:O42) -> 240000001
A43: 2025 | B43: 1001.02.00 | C43: =_xlfn.XLOOKUP(B43, 'Revenue Codes'!$A$2:$A$99, 'Revenue Codes'!$B$2:$B$99, "") -> Export Duty | D43: 2000 | E43: 2000 | F43: 1000 | G43: 2245 | H43: 2845 | I43: 2925 | J43: 3083 | K43: 3004 | L43: 2925 | M43: 3241 | N43: 3320 | O43: 3414 | P43: =SUM(D43:O43) -> 32002
A44: 2025 | B44: 1001.04.00 | C44: =_xlfn.XLOOKUP(B44, 'Revenue Codes'!$A$2:$A$99, 'Revenue Codes'!$B$2:$B$99, "") -> PAL | D44: 12895000 | E44: 13031000 | F44: 15367000 | G44: 11996424 | H44: 15195044 | I44: 15615915 | J44: 16457657 | K44: 16036786 | L44: 15615915 | M44: 17299399 | N44: 17720269 | O44: 17769591 | P44: =SUM(D44:O44) -> 185000000
A45: 2025 | B45: 1001.05.01 | C45: =_xlfn.XLOOKUP(B45, 'Revenue Codes'!$A$2:$A$99, 'Revenue Codes'!$B$2:$B$99, "") -> Cess (Import) | D45: 7113000 | E45: 7404000 | F45: 6303000 | G45: 6399297 | H45: 8112795 | I45: 8338245 | J45: 8789143 | K45: 8563694 | L45: 8338245 | M45: 9240042 | N45: 9465491 | O45: 9733047 | P45: =SUM(D45:O45) -> 97799999
A46: 2025 | B46: 1001.05.02 | C46: =_xlfn.XLOOKUP(B46, 'Revenue Codes'!$A$2:$A$99, 'Revenue Codes'!$B$2:$B$99, "") -> Cess (Export) | D46: 101000 | E46: 86000 | F46: 101000 | G46: 158945 | H46: 201503 | I46: 207102 | J46: 218301 | K46: 212702 | L46: 207102 | M46: 229501 | N46: 235100 | O46: 241744 | P46: =SUM(D46:O46) -> 2200000
A47: 2025 | B47: 1001.08.00 | C47: =_xlfn.XLOOKUP(B47, 'Revenue Codes'!$A$2:$A$99, 'Revenue Codes'!$B$2:$B$99, "") -> SCL | D47: 19302000 | E47: 13129000 | F47: 15461000 | G47: 6493151 | H47: 8231673 | I47: 8460426 | J47: 8917932 | K47: 8689179 | L47: 8460426 | M47: 9375438 | N47: 9604068 | O47: 9875707 | P47: =SUM(D47:O47) -> 126000000
A48: 2025 | B48: 1002.01.04 | C48: =_xlfn.XLOOKUP(B48, 'Revenue Codes'!$A$2:$A$99, 'Revenue Codes'!$B$2:$B$99, "") -> VAT | D48: 53082000 | E48: 49041000 | F48: 50346000 | G48: 52998224 | H48: 67188236 | I48: 69055462 | J48: 72789703 | K48: 70922471 | L48: 69055462 | M48: 76523945 | N48: 78391064 | O48: 80606434 | P48: =SUM(D48:O48) -> 790000001
A49: 2025 | B49: 1002.16.03 | C49: =_xlfn.XLOOKUP(B49, 'Revenue Codes'!$A$2:$A$99, 'Revenue Codes'!$B$2:$B$99, "") -> SSL | D49: 5960000 | E49: 5412000 | F49: 4985000 | G49: 4791887 | H49: 6074901 | I49: 6243718 | J49: 6581239 | K49: 6412536 | L49: 6243718 | M49: 6918989 | N49: 7087806 | O49: 7288206 | P49: =SUM(D49:O49) -> 74000000
A50: 2025 | B50: 1002.05.01 | C50: =_xlfn.XLOOKUP(B50, 'Revenue Codes'!$A$2:$A$99, 'Revenue Codes'!$B$2:$B$99, "") -> Cigarette | D50: 11426000 | E50: 8631000 | F50: 6330000 | G50: 8613393 | H50: 10919603 | I50: 11222944 | J50: 11829949 | K50: 11526501 | L50: 11223052 | M50: 12436727 | N50: 12740295 | O50: 13100535 | P50: =SUM(D50:O50) -> 129999999
A51: 2025 | B51: 1002.05.03 | C51: =_xlfn.XLOOKUP(B51, 'Revenue Codes'!$A$2:$A$99, 'Revenue Codes'!$B$2:$B$99, "") -> Petroleum Products | D51: 15041000 | E51: 16526000 | F51: 16389000 | G51: 15133395 | H51: 19185317 | I51: 19718465 | J51: 20784760 | K51: 20251612 | L51: 19718465 | M51: 21851055 | N51: 22384202 | O51: 23016729 | P51: =SUM(D51:O51) -> 230000000
A52: 2025 | B52: 1002.05.04 | C52: =_xlfn.XLOOKUP(B52, 'Revenue Codes'!$A$2:$A$99, 'Revenue Codes'!$B$2:$B$99, "") -> Motor Vehicles | D52: 6018000 | E52: 1140000 | F52: 10025000 | G52: 17691568 | H52: 22428433 | I52: 23051704 | J52: 24298248 | K52: 23674976 | L52: 23051596 | M52: 25544791 | N52: 26168062 | O52: 26907620 | P52: =SUM(D52:O52) -> 229999998
A53: 2025 | B53: 1002.05.99 | C53: =_xlfn.XLOOKUP(B53, 'Revenue Codes'!$A$2:$A$99, 'Revenue Codes'!$B$2:$B$99, "") -> Excise (Other) | D53: 1384000 | E53: 732000 | F53: 2950000 | G53: 327035 | H53: 414598 | I53: 426119 | J53: 449162 | K53: 437641 | L53: 426119 | M53: 472205 | N53: 483726 | O53: 497395 | P53: =SUM(D53:O53) -> 9000000
... A61: 2025 | B61: 2003.99.00 | C61: =_xlfn.XLOOKUP(B61, 'Revenue Codes'!$A$2:$A$99, 'Revenue Codes'!$B$2:$B$99, "") -> Other Receipts | D61: 8333 | E61: 8334 | F61: 8333 | G61: 8333 | H61: 8334 | I61: 8333 | J61: 8333 | K61: 8334 | L61: 8333 | M61: 8333 | N61: 8334 | O61: 8333 | P61: =SUM(D61:O61) -> 100000
A62: 2026 | B62: 1001.01.00 | C62: =_xlfn.XLOOKUP(B62, 'Revenue Codes'!$A$2:$A$99, 'Revenue Codes'!$B$2:$B$99, "") -> Import Duty | D62: 9577000 | E62: 10766000 | F62: 11611000 | G62: 17294953 | H62: 21304292 | I62: 22534924 | J62: 23753522 | K62: 23144223 | L62: 22534924 | M62: 24972120 | N62: 25581417 | O62: 21925625 | P62: 235000000
A63: 2026 | B63: 1001.02.00 | C63: =_xlfn.XLOOKUP(B63, 'Revenue Codes'!$A$2:$A$99, 'Revenue Codes'!$B$2:$B$99, "") -> Export Duty | D63: 2000 | E63: 2000 | F63: 2000 | G63: 3245 | H63: 2412 | I63: 2925 | J63: 3083 | K63: 3004 | L63: 3925 | M63: 3241 | N63: 3320 | O63: 3845 | P63: 35000
A64: 2026 | B64: 1001.04.00 | C64: =_xlfn.XLOOKUP(B64, 'Revenue Codes'!$A$2:$A$99, 'Revenue Codes'!$B$2:$B$99, "") -> PAL | D64: 13895000 | E64: 13031000 | F64: 15367000 | G64: 14996424 | H64: 17769591 | I64: 15615915 | J64: 16457657 | K64: 16036786 | L64: 16615915 | M64: 17299399 | N64: 17720269 | O64: 15195044 | P64: 190000000
A65: 2026 | B65: 1001.05.01 | C65: =_xlfn.XLOOKUP(B65, 'Revenue Codes'!$A$2:$A$99, 'Revenue Codes'!$B$2:$B$99, "") -> Cess (Import) | D65: 7113000 | E65: 7404000 | F65: 6303000 | G65: 6399297 | H65: 6533248 | I65: 7338245 | J65: 7789143 | K65: 7563694 | L65: 8338245 | M65: 7240042 | N65: 8465291 | O65: 7112795 | P65: 87600000
A66: 2026 | B66: 1001.05.02 | C66: =_xlfn.XLOOKUP(B66, 'Revenue Codes'!$A$2:$A$99, 'Revenue Codes'!$B$2:$B$99, "") -> Cess (Export) | D66: 221000 | E66: 226000 | F66: 221000 | G66: 258945 | H66: 141744 | I66: 207102 | J66: 218301 | K66: 212702 | L66: 107102 | M66: 229501 | N66: 155100 | O66: 201503 | P66: 2400000
A67: 2026 | B67: 1001.08.00 | C67: =_xlfn.XLOOKUP(B67, 'Revenue Codes'!$A$2:$A$99, 'Revenue Codes'!$B$2:$B$99, "") -> SCL | D67: 11302000 | E67: 13129000 | F67: 15461000 | G67: 9493151 | H67: 9875707 | I67: 9460426 | J67: 10917932 | K67: 9689179 | L67: 10460426 | M67: 9375438 | N67: 9604068 | O67: 10231673 | P67: 129000000
A68: 2026 | B68: 1002.01.04 | C68: =_xlfn.XLOOKUP(B68, 'Revenue Codes'!$A$2:$A$99, 'Revenue Codes'!$B$2:$B$99, "") -> VAT | D68: 61188236 | E68: 68041000 | F68: 76346000 | G68: 75998224 | H68: 75606433 | I68: 71055462 | J68: 74789703 | K68: 72922471 | L68: 77055462 | M68: 76523945 | N68: 76391064 | O68: 69082000 | P68: 875000000
A69: 2026 | B69: 1002.16.03 | C69: =_xlfn.XLOOKUP(B69, 'Revenue Codes'!$A$2:$A$99, 'Revenue Codes'!$B$2:$B$99, "") -> SSL | D69: 8960000 | E69: 8412000 | F69: 8985000 | G69: 7791887 | H69: 7288206 | I69: 8243718 | J69: 7581239 | K69: 8412536 | L69: 8243718 | M69: 8918989 | N69: 7087806 | O69: 7074901 | P69: 97000000
A70: 2026 | B70: 1002.05.01 | C70: =_xlfn.XLOOKUP(B70, 'Revenue Codes'!$A$2:$A$99, 'Revenue Codes'!$B$2:$B$99, "") -> Cigarette | D70: 8426000 | E70: 8631000 | F70: 6330000 | G70: 8613393 | H70: 9100536 | I70: 9222944 | J70: 8829949 | K70: 10526501 | L70: 9223052 | M70: 7436727 | N70: 9740295 | O70: 8919603 | P70: 105000000
A71: 2026 | B71: 1002.05.03 | C71: =_xlfn.XLOOKUP(B71, 'Revenue Codes'!$A$2:$A$99, 'Revenue Codes'!$B$2:$B$99, "") -> Petroleum Products | D71: 16041000 | E71: 12526000 | F71: 16389000 | G71: 17133395 | H71: 17016729 | I71: 17718465 | J71: 18784760 | K71: 18251612 | L71: 19718465 | M71: 17851055 | N71: 16384202 | O71: 17185317 | P71: 205000000
A72: 2026 | B72: 1002.05.04 | C72: =_xlfn.XLOOKUP(B72, 'Revenue Codes'!$A$2:$A$99, 'Revenue Codes'!$B$2:$B$99, "") -> Motor Vehicles | D72: 22100000 | E72: 22300000 | F72: 22100000 | G72: 22100000 | H72: 22100000 | I72: 22300000 | J72: 22100000 | K72: 22300000 | L72: 22100000 | M72: 22200000 | N72: 22100000 | O72: 22200000 | P72: 266000000
A73: 2026 | B73: 1002.05.99 | C73: =_xlfn.XLOOKUP(B73, 'Revenue Codes'!$A$2:$A$99, 'Revenue Codes'!$B$2:$B$99, "") -> Excise (Other) | D73: 1284000 | E73: 1332000 | F73: 1150000 | G73: 1027035 | H73: 897395 | I73: 1026119 | J73: 1049162 | K73: 1037641 | L73: 1026119 | M73: 1072205 | N73: 1083726 | O73: 1014598 | P73: 13000000
A74: 2026 | B74: 1003.07.10 | C74: =_xlfn.XLOOKUP(B74, 'Revenue Codes'!$A$2:$A$99, 'Revenue Codes'!$B$2:$B$99, "") -> VEL | D74: 64000 | E74: 75000 | F74: 66000 | G74: 94402 | H74: 93158 | I74: 96944 | J74: 102186 | K74: 99565 | L74: 96944 | M74: 107428 | N74: 110050 | O74: 94323 | P74: 1100000
A75: 2026 | B75: 1002.12.03 | C75: =_xlfn.XLOOKUP(B75, 'Revenue Codes'!$A$2:$A$99, 'Revenue Codes'!$B$2:$B$99, "") -> NBT | D75: - | E75: - | F75: - | G75: - | H75: - | I75: - | J75: - | K75: - | L75: - | M75: - | N75: - | O75: - | P75: 0
A76: 2026 | B76: 1003.01.00 | C76: =_xlfn.XLOOKUP(B76, 'Revenue Codes'!$A$2:$A$99, 'Revenue Codes'!$B$2:$B$99, "") -> LXT | D76: 8000 | E76: 8000 | F76: 8000 | G76: 8000 | H76: 9000 | I76: 8000 | J76: 9000 | K76: 8000 | L76: 9000 | M76: 8000 | N76: 9000 | O76: 8000 | P76: 100000
A77: 2026 | B77: 1004.04.02 | C77: =_xlfn.XLOOKUP(B77, 'Revenue Codes'!$A$2:$A$99, 'Revenue Codes'!$B$2:$B$99, "") -> ESC | D77: - | E77: - | F77: - | G77: - | H77: - | I77: - | J77: - | K77: - | L77: - | M77: - | N77: - | O77: - | P77: -
A78: 2026 | B78: 2003.02.99 | C78: =_xlfn.XLOOKUP(B78, 'Revenue Codes'!$A$2:$A$99, 'Revenue Codes'!$B$2:$B$99, "") -> Sundris & Others | D78: 8000 | E78: 8000 | F78: 9000 | G78: 8000 | H78: 9000 | I78: 8000 | J78: 8000 | K78: 9000 | L78: 8000 | M78: 9000 | N78: 8000 | O78: 8000 | P78: 100000
A79: 2026 | B79: 2003.03.01 | C79: =_xlfn.XLOOKUP(B79, 'Revenue Codes'!$A$2:$A$99, 'Revenue Codes'!$B$2:$B$99, "") -> Fine & Forfeits | D79: 41000 | E79: 42000 | F79: 42000 | G79: 42000 | H79: 42000 | I79: 43000 | J79: 42000 | K79: 44000 | L79: 42000 | M79: 46000 | N79: 42000 | O79: 42000 | P79: 510000
A80: 2026 | B80: 2003.02.17 | C80: =_xlfn.XLOOKUP(B80, 'Revenue Codes'!$A$2:$A$99, 'Revenue Codes'!$B$2:$B$99, "") -> Sales of Garment | D80: 4000 | E80: 4000 | F80: 4000 | G80: 4000 | H80: 4000 | I80: 4000 | J80: 5000 | K80: 4000 | L80: 5000 | M80: 4000 | N80: 4000 | O80: 4000 | P80: 50000
A81: 2026 | B81: 2003.99.00 | C81: =_xlfn.XLOOKUP(B81, 'Revenue Codes'!$A$2:$A$99, 'Revenue Codes'!$B$2:$B$99, "") -> Other Receipts | E81: 8000 | F81: 8000 | G81: 8000 | H81: 8000 | I81: 9000 | J81: 8000 | K81: 9000 | L81: 8000 | M81: 9000 | N81: 9000 | O81: 8000 | P81: 100000
A82: 2023 | B82: 1001.01.00 | C82: =_xlfn.XLOOKUP(B82, 'Revenue Codes'!$A$2:$A$99, 'Revenue Codes'!$B$2:$B$99, "") -> Import Duty | D82: 3279000 | E82: 4393000 | F82: 4687000 | G82: 3121000 | H82: 3299000 | I82: 3799000 | J82: 2616000 | K82: 3182000 | L82: 4315000 | M82: 5302000 | N82: 3195000 | O82: 3199000 | P82: =SUM(D82:O82) -> 44387000
A83: 2023 | B83: 1001.01.00 | C83: =_xlfn.XLOOKUP(B83, 'Revenue Codes'!$A$2:$A$99, 'Revenue Codes'!$B$2:$B$99, "") -> Import Duty | P83: =SUM(D83:O83) -> 0
A84: 2023 | B84: 1001.02.00 | C84: =_xlfn.XLOOKUP(B84, 'Revenue Codes'!$A$2:$A$99, 'Revenue Codes'!$B$2:$B$99, "") -> Export Duty | D84: 2770 | E84: 17550 | F84: 6070 | G84: 1740 | H84: 3520 | I84: 2790 | J84: 3090 | K84: 2970 | L84: 3020 | M84: 3000 | N84: 3000 | O84: 3000 | P84: =SUM(D84:O84) -> 52520
A85: 2023 | B85: 1001.04.00 | C85: =_xlfn.XLOOKUP(B85, 'Revenue Codes'!$A$2:$A$99, 'Revenue Codes'!$B$2:$B$99, "") -> PAL | D85: 12460000 | E85: 12560000 | F85: 13054750 | G85: 13460860 | H85: 13214180 | I85: 13617690 | J85: 13373600 | K85: 12650000 | L85: 13250000 | M85: 14640000 | N85: 13692410 | O85: 13088000 | P85: =SUM(D85:O85) -> 159061490
A86: 2023 | B86: 1001.05.01 | C86: =_xlfn.XLOOKUP(B86, 'Revenue Codes'!$A$2:$A$99, 'Revenue Codes'!$B$2:$B$99, "") -> Cess (Import) | D86: 3581510 | E86: 5022450 | F86: 5974020 | G86: 4814120 | H86: 4744900 | I86: 4752590 | J86: 4765710 | K86: 4779200 | L86: 4792720 | M86: 4806250 | N86: 4819770 | O86: 4810000 | P86: =SUM(D86:O86) -> 57663240
A87: 2023 | B87: 1001.05.02 | C87: =_xlfn.XLOOKUP(B87, 'Revenue Codes'!$A$2:$A$99, 'Revenue Codes'!$B$2:$B$99, "") -> Cess (Export) | D87: 65890 | E87: 90470 | F87: 129030 | G87: 87080 | H87: 104070 | I87: 94960 | J87: 97410 | K87: 94740 | L87: 94330 | M87: 92930 | N87: 91960 | O87: 90800 | P87: =SUM(D87:O87) -> 1133670
A88: 2023 | B88: 1001.08.00 | C88: =_xlfn.XLOOKUP(B88, 'Revenue Codes'!$A$2:$A$99, 'Revenue Codes'!$B$2:$B$99, "") -> SCL | D88: 3080000 | E88: 3240000 | F88: 3327630 | G88: 2850000 | H88: 3200000 | I88: 3125000 | J88: 3250000 | K88: 3640000 | L88: 3090000 | M88: 3750000 | N88: 2560000 | O88: 2650000 | P88: =SUM(D88:O88) -> 37762630
A89: 2023 | B89: 1002.01.04 | C89: =_xlfn.XLOOKUP(B89, 'Revenue Codes'!$A$2:$A$99, 'Revenue Codes'!$B$2:$B$99, "") -> VAT | D89: 13885990 | E89: 13342410 | F89: 15098190 | G89: 14311350 | H89: 14755280 | I89: 14703900 | J89: 14851850 | K89: 14919590 | L89: 15019600 | M89: 15106630 | N89: 15198880 | O89: 15289030 | P89: =SUM(D89:O89) -> 176482700
A90: 2023 | B90: 1002.05.01 | C90: =_xlfn.XLOOKUP(B90, 'Revenue Codes'!$A$2:$A$99, 'Revenue Codes'!$B$2:$B$99, "") -> Cigarette | D90: 8854670 | E90: 8569710 | F90: 9012130 | G90: 8296690 | H90: 8973890 | I90: 8357220 | J90: 8942660 | K90: 8411240 | L90: 8917470 | M90: 8459640 | N90: 8897500 | O90: 8503200 | P90: =SUM(D90:O90) -> 104196020
A91: 2023 | B91: 1002.05.02 | C91: =_xlfn.XLOOKUP(B91, 'Revenue Codes'!$A$2:$A$99, 'Revenue Codes'!$B$2:$B$99, "") -> Liquor | P91: =SUM(D91:O91) -> 0
A92: 2023 | B92: 1002.05.03 | C92: =_xlfn.XLOOKUP(B92, 'Revenue Codes'!$A$2:$A$99, 'Revenue Codes'!$B$2:$B$99, "") -> Petroleum Products | D92: 3850000 | E92: 3528590 | F92: 2693200 | G92: 2986030 | H92: 3012000 | I92: 2959860 | J92: 2965320 | K92: 2972330 | L92: 2979080 | M92: 2985870 | N92: 3552000 | O92: 2999450 | P92: =SUM(D92:O92) -> 37483730
A93: 2023 | B93: 1002.05.04 | C93: =_xlfn.XLOOKUP(B93, 'Revenue Codes'!$A$2:$A$99, 'Revenue Codes'!$B$2:$B$99, "") -> Motor Vehicles | D93: 100170 | E93: 2043000 | F93: 2006680 | G93: 274000 | H93: 345000 | I93: 509000 | J93: 670000 | K93: 830000 | L93: 991000 | M93: 1152000 | N93: 1312000 | O93: 1473000 | P93: =SUM(D93:O93) -> 11705850
A94: 2023 | B94: 1002.05.99 | C94: =_xlfn.XLOOKUP(B94, 'Revenue Codes'!$A$2:$A$99, 'Revenue Codes'!$B$2:$B$99, "") -> Excise (Other) | D94: 456320 | E94: 689590 | F94: 168310 | G94: 370890 | H94: 399210 | I94: 406130 | J94: 410420 | K94: 414390 | L94: 418320 | M94: 422250 | N94: 426170 | O94: 430100 | P94: =SUM(D94:O94) -> 5012100
A95: 2023 | B95: 1002.12.03 | C95: =_xlfn.XLOOKUP(B95, 'Revenue Codes'!$A$2:$A$99, 'Revenue Codes'!$B$2:$B$99, "") -> NBT | D95: 1000 | E95: 1000 | F95: 1000 | G95: 300 | H95: 400 | I95: 1000 | J95: 1000 | K95: 500 | L95: 1000 | M95: 1000 | N95: 1000 | O95: 1000 | P95: =SUM(D95:O95) -> 10200
A96: 2023 | B96: 1003.07.10 | C96: =_xlfn.XLOOKUP(B96, 'Revenue Codes'!$A$2:$A$99, 'Revenue Codes'!$B$2:$B$99, "") -> VEL | D96: 5000 | E96: 4000 | F96: 6000 | G96: 6000 | H96: 5000 | I96: 7000 | J96: 6000 | K96: 7000 | L96: 4000 | M96: 9000 | N96: 7000 | O96: 7000 | P96: =SUM(D96:O96) -> 73000
A97: 2023 | B97: 1004.04.02 | C97: =_xlfn.XLOOKUP(B97, 'Revenue Codes'!$A$2:$A$99, 'Revenue Codes'!$B$2:$B$99, "") -> ESC | D97: 1000 | E97: 500 | F97: 400 | G97: 1200 | H97: 400 | I97: 1300 | J97: 200 | K97: 600 | L97: 400 | M97: 200 | N97: 300 | O97: 1200 | P97: =SUM(D97:O97) -> 7700
A98: 2023 | B98: 2003.02.17 | C98: =_xlfn.XLOOKUP(B98, 'Revenue Codes'!$A$2:$A$99, 'Revenue Codes'!$B$2:$B$99, "") -> Sales of Garment | D98: 4000 | E98: 6480 | F98: 22630 | G98: 6470 | H98: 9470 | I98: 10000 | J98: 9020 | K98: 12000 | L98: 9000 | M98: 15000 | N98: 10000 | O98: 9000 | P98: =SUM(D98:O98) -> 123070
A99: 2023 | B99: 2003.03.01 | C99: =_xlfn.XLOOKUP(B99, 'Revenue Codes'!$A$2:$A$99, 'Revenue Codes'!$B$2:$B$99, "") -> Fine & Forfeits | D99: 125160 | E99: 187990 | F99: 250000 | G99: 220660 | H99: 233590 | I99: 234890 | J99: 236550 | K99: 238200 | L99: 239850 | M99: 241500 | N99: 243150 | O99: 244800 | P99: =SUM(D99:O99) -> 2696340
A100: 2023 | B100: 2003.02.99 | C100: =_xlfn.XLOOKUP(B100, 'Revenue Codes'!$A$2:$A$99, 'Revenue Codes'!$B$2:$B$99, "") -> Sundris & Others | D100: 13000 | E100: 10730 | F100: 10000 | G100: 12000 | H100: 15000 | I100: 22000 | J100: 28280 | K100: 15000 | L100: 16910 | M100: 10000 | N100: 23000 | O100: 15000 | P100: =SUM(D100:O100) -> 190920
A101: 2023 | B101: 1003.01.00 | C101: =_xlfn.XLOOKUP(B101, 'Revenue Codes'!$A$2:$A$99, 'Revenue Codes'!$B$2:$B$99, "") -> LXT | D101: 37000 | E101: 36000 | F101: 35000 | G101: 26000 | H101: 19000 | I101: 14000 | J101: 98000 | K101: 63000 | L101: 35000 | M101: 13000 | N101: 37190 | O101: 177440 | P101: =SUM(D101:O101) -> 590630
A102: 2023 | B102: 2003.99.00 | C102: =_xlfn.XLOOKUP(B102, 'Revenue Codes'!$A$2:$A$99, 'Revenue Codes'!$B$2:$B$99, "") -> Other Receipts | D102: 3000 | E102: 4000 | F102: 2380 | G102: 1440 | H102: 3000 | I102: 1250 | J102: 5000 | K102: 4000 | L102: 3000 | M102: 6000 | N102: 4000 | O102: 2000 | P102: =SUM(D102:O102) -> 39070
A103: 2021 | B103: 1001.01.00 | C103: =_xlfn.XLOOKUP(B103, 'Revenue Codes'!$A$2:$A$99, 'Revenue Codes'!$B$2:$B$99, "") -> Import Duty | D103: 1430720 | E103: 1474310 | F103: 1484540 | G103: 1367650 | H103: 1424380 | I103: 1570680 | J103: 1544380 | K103: 1452990 | L103: 1477010 | M103: 1599650 | N103: 1502820 | O103: 1670870 | P103: =SUM(D103:O103) -> 18000000
... A115: 2021 | B115: 1003.01.00 | C115: =_xlfn.XLOOKUP(B115, 'Revenue Codes'!$A$2:$A$99, 'Revenue Codes'!$B$2:$B$99, "") -> LXT | D115: 17300 | E115: 18500 | F115: 17900 | G115: 18700 | H115: 17800 | I115: 18500 | J115: 18300 | K115: 17600 | L115: 17900 | M115: 18400 | N115: 18500 | O115: 18800 | P115: =SUM(D115:O115) -> 218200
A116: 2021 | B116: 1002.12.03 | C116: =_xlfn.XLOOKUP(B116, 'Revenue Codes'!$A$2:$A$99, 'Revenue Codes'!$B$2:$B$99, "") -> NBT | D116: 600 | E116: 600 | F116: 600 | H116: 100 | I116: 400 | J116: 500 | K116: 500 | L116: 500 | M116: 500 | N116: 500 | O116: 500 | P116: =SUM(D116:O116) -> 5300
A117: 2021 | B117: 1004.04.02 | C117: =_xlfn.XLOOKUP(B117, 'Revenue Codes'!$A$2:$A$99, 'Revenue Codes'!$B$2:$B$99, "") -> ESC | P117: =SUM(D117:O117) -> 0
A118: 2021 | B118: 2003.02.17 | C118: =_xlfn.XLOOKUP(B118, 'Revenue Codes'!$A$2:$A$99, 'Revenue Codes'!$B$2:$B$99, "") -> Sales of Garment | D118: 1000 | E118: 1400 | F118: 2400 | G118: 1200 | H118: 1400 | I118: 1300 | J118: 1100 | K118: 600 | L118: 1200 | M118: 600 | N118: 1200 | O118: 1000 | P118: =SUM(D118:O118) -> 14400
A119: 2021 | B119: 2003.03.01 | C119: =_xlfn.XLOOKUP(B119, 'Revenue Codes'!$A$2:$A$99, 'Revenue Codes'!$B$2:$B$99, "") -> Fine & Forfeits | D119: 30600 | E119: 30800 | F119: 31100 | G119: 31300 | H119: 31500 | I119: 31700 | J119: 31900 | K119: 32100 | L119: 32300 | M119: 32600 | N119: 32800 | O119: 33000 | P119: =SUM(D119:O119) -> 381700
A120: 2021 | B120: 2003.02.99 | C120: =_xlfn.XLOOKUP(B120, 'Revenue Codes'!$A$2:$A$99, 'Revenue Codes'!$B$2:$B$99, "") -> Sundris & Others | D120: 3100 | E120: 3100 | F120: 3000 | G120: 3300 | H120: 3300 | I120: 3000 | J120: 3000 | K120: 3100 | L120: 3100 | M120: 3000 | N120: 3400 | O120: 3100 | P120: =SUM(D120:O120) -> 37500
A121: 2021 | B121: 2003.99.00 | C121: =_xlfn.XLOOKUP(B121, 'Revenue Codes'!$A$2:$A$99, 'Revenue Codes'!$B$2:$B$99, "") -> Other Receipts | D121: 1500 | E121: 1500 | F121: 1500 | G121: 1500 | H121: 1500 | I121: 1500 | J121: 1500 | K121: 1500 | L121: 1500 | M121: 1500 | N121: 1500 | O121: 1500 | P121: =SUM(D121:O121) -> 18000
A122: 2020 | B122: 1001.01.00 | C122: =_xlfn.XLOOKUP(B122, 'Revenue Codes'!$A$2:$A$99, 'Revenue Codes'!$B$2:$B$99, "") -> Import Duty | D122: 778800 | E122: 762200 | F122: 810600 | G122: 748900 | H122: 597900 | I122: 554400 | J122: 644500 | K122: 921000 | L122: 960900 | M122: 986500 | N122: 1001200 | O122: 1009300 | P122: =SUM(D122:O122) -> 9776200
A123: 2020 | B123: 1001.02.00 | C123: =_xlfn.XLOOKUP(B123, 'Revenue Codes'!$A$2:$A$99, 'Revenue Codes'!$B$2:$B$99, "") -> Export Duty | D123: 400 | E123: 400 | F123: 500 | G123: 400 | H123: 600 | I123: 600 | J123: 500 | K123: 500 | L123: 600 | M123: 700 | N123: 700 | O123: 800 | P123: =SUM(D123:O123) -> 6700
A124: 2020 | B124: 1001.04.00 | C124: =_xlfn.XLOOKUP(B124, 'Revenue Codes'!$A$2:$A$99, 'Revenue Codes'!$B$2:$B$99, "") -> PAL | D124: 752000 | E124: 836400 | F124: 923000 | G124: 768200 | H124: 638400 | I124: 592000 | J124: 688000 | K124: 621100 | L124: 721500 | M124: 774800 | N124: 828800 | O124: 834300 | P124: =SUM(D124:O124) -> 8978500
A125: 2020 | B125: 1001.05.01 | C125: =_xlfn.XLOOKUP(B125, 'Revenue Codes'!$A$2:$A$99, 'Revenue Codes'!$B$2:$B$99, "") -> Cess (Import) | D125: 342450 | E125: 344240 | F125: 346040 | G125: 327800 | H125: 359100 | I125: 333000 | J125: 387000 | K125: 485400 | L125: 615300 | M125: 467000 | N125: 431700 | O125: 599700 | P125: =SUM(D125:O125) -> 5038730
A126: 2020 | B126: 1001.05.02 | C126: =_xlfn.XLOOKUP(B126, 'Revenue Codes'!$A$2:$A$99, 'Revenue Codes'!$B$2:$B$99, "") -> Cess (Export) | D126: 15900 | E126: 16800 | F126: 15700 | G126: 16200 | H126: 79800 | I126: 74000 | J126: 86000 | K126: 16400 | L126: 17100 | M126: 17500 | N126: 17700 | O126: 17800 | P126: =SUM(D126:O126) -> 390900
A127: 2020 | B127: 1001.08.00 | C127: =_xlfn.XLOOKUP(B127, 'Revenue Codes'!$A$2:$A$99, 'Revenue Codes'!$B$2:$B$99, "") -> SCL | D127: 481600 | E127: 457540 | F127: 510200 | G127: 462820 | H127: 518700 | I127: 481000 | J127: 559000 | K127: 630900 | L127: 653500 | M127: 668500 | N127: 677300 | O127: 682300 | P127: =SUM(D127:O127) -> 6783360
A128: 2020 | B128: 1003.01.00 | C128: =_xlfn.XLOOKUP(B128, 'Revenue Codes'!$A$2:$A$99, 'Revenue Codes'!$B$2:$B$99, "") -> LXT | D128: 15400 | E128: 14500 | F128: 13700 | G128: 10800 | H128: 99800 | I128: 92500 | J128: 107500 | K128: 14300 | L128: 14800 | M128: 15200 | N128: 15400 | O128: 15500 | P128: =SUM(D128:O128) -> 429400
A129: 2020 | B129: 1002.01.04 | C129: =_xlfn.XLOOKUP(B129, 'Revenue Codes'!$A$2:$A$99, 'Revenue Codes'!$B$2:$B$99, "") -> VAT | D129: 587740 | E129: 592200 | F129: 596660 | G129: 601130 | H129: 758100 | I129: 703000 | J129: 817000 | K129: 787200 | L129: 685700 | M129: 863900 | N129: 904900 | O129: 774700 | P129: =SUM(D129:O129) -> 8672230
...

Sheet Daily Revenue
A1: Date | B1: Cash reveres | C1: Vat Refund | D1: BOC 7041607 | E1: BOC 7041608 | F1: DST 2026450 | G1: PB 9026645 | H1: PB 59025247 | I1: DST 30110432 | J1: Total | K1: Cumulative Total | L1: Daily Target | M1: Cumulative Target | N1: Percentage Achieved | R1: Instructions
A2: 43831 | R2: 1) Holidays should be entered in the Holidays sheet. Relevant days are automatically updated. 2) Enter all values in exact figures LKR (Not is millions, '000, billion etc.) 3) Values entered in this shared Excel automatically updates the Revenue Dashboard. If any errors in the dashboard is noticed, check values in this Excel Sheet.
A3: 43832
A4: 43833
A5: 43834
A6: 43835
A7: 43836
A8: 43837
A9: 43838
A10: 43839
A11: 43840
A12: 43841
A13: 43842
A14: 43843
... A1097: 44926
A1098: 44927 | D1098: - | E1098: - | F1098: - | G1098: 6694264 | H1098: - | I1098: 6694264 | J1098: 6694264 | M1098: -
A1099: 44928 | D1099: 1533584412 | E1099: - | F1099: 1533584412 | G1099: 90919983 | H1099: - | I1099: 90919983 | J1099: 1624504395 | M1099: 2406000000
A1100: 44929 | D1100: 1946200624 | F1100: 1946200624 | G1100: 98557515 | H1100: 8500000000 | I1100: 8598557515 | J1100: 10544758139 | M1100: 4809000000
A1101: 44930 | D1101: 2253347382 | F1101: 2253347382 | G1101: 79743668 | H1101: 51913400 | I1101: 131657068 | J1101: 2385004450 | M1101: 7217000000
A1102: 44931 | D1102: 4.0754921e+09 | F1102: 4.0754921e+09 | G1102: 87839191 | H1102: 100000000 | I1102: 187839191 | J1102: 4.2633313e+09 | M1102: 9723000000
A1103: 44932 | D1103: - | F1103: - | G1103: 5366963 | H1103: - | I1103: 5366963 | J1103: 5366963 | M1103: 9723000000
A1104: 44933 | D1104: - | F1104: - | G1104: 1100850 | H1104: - | I1104: 1100850 | J1104: 1100850 | M1104: 9723000000
A1105: 44934 | D1105: - | F1105: - | G1105: - | I1105: - | J1105: - | M1105: 9723000000
A1106: 44935 | D1106: 2.5221205e+09 | F1106: 2.5221205e+09 | G1106: 107455057 | I1106: 107455057 | J1106: 2.6295756e+09 | M1106: 11994000000
A1107: 44936 | D1107: 2082499521 | F1107: 2082499521 | G1107: 202826142 | I1107: 202826142 | J1107: 2285325663 | M1107: 14424000000
A1108: 44937 | D1108: 2891698773 | E1108: 803399 | F1108: 2892502172 | G1108: 140158352 | I1108: 140158352 | J1108: 3032660524 | M1108: 16866000000
A1109: 44938 | D1109: 2.1391204e+09 | E1109: 4834409 | F1109: 2.1439548e+09 | G1109: 76039743 | I1109: 76039743 | J1109: 2.2199946e+09 | M1109: 19286000000
A1110: 44939 | D1110: 1801734336 | F1110: 1801734336 | G1110: 167004014 | H1110: 100000000 | I1110: 267004014 | J1110: 2068738350 | M1110: 33240000000
A1111: 44940 | F1111: - | G1111: 2200 | I1111: 2200 | J1111: 2200 | M1111: 33240000000
A1112: 44941 | F1112: - | I1112: - | J1112: - | M1112: 33240000000
A1113: 44942 | F1113: - | G1113: 4028274 | I1113: 4028274 | J1113: 4028274 | M1113: 35645000000
A1114: 44943 | D1114: 2593842758 | E1114: 278648 | F1114: 2594121406 | G1114: 99783072 | I1114: 99783072 | J1114: 2693904478 | M1114: 38046000000
A1115: 44944 | D1115: 2751051294 | E1115: 251188.5 | F1115: 2.7513025e+09 | G1115: 143366058 | I1115: 143366058 | J1115: 2.8946685e+09 | M1115: 40452000000
A1116: 44945 | D1116: 2162300666 | E1116: 6134828 | F1116: 2168435494 | G1116: 102718771 | I1116: 102718771 | J1116: 2271154265 | M1116: 42860000000
A1117: 44946 | D1117: 1777717383 | E1117: 6670640 | F1117: 1784388023 | G1117: 107140628 | H1117: 100000000 | I1117: 207140628 | J1117: 1991528651 | M1117: 45373000000
A1118: 44947 | F1118: - | G1118: 2184459 | H1118: - | I1118: 2184459 | J1118: 2184459 | M1118: 45373000000
A1119: 44948 | F1119: - | G1119: - | H1119: - | I1119: - | J1119: - | M1119: 45373000000
A1120: 44949 | D1120: 2.9025835e+09 | E1120: - | F1120: 2.9025835e+09 | G1120: 56770087 | H1120: - | I1120: 56770087 | J1120: 2.9593536e+09 | M1120: 47781000000
A1121: 44950 | D1121: 2327667728 | E1121: - | F1121: 2327667728 | G1121: 112994445 | H1121: - | I1121: 112994445 | J1121: 2440662173 | M1121: 50187000000
A1122: 44951 | D1122: 3496762111 | E1122: 2432215.5 | F1122: 3.4991943e+09 | G1122: 162361825 | H1122: - | I1122: 162361825 | J1122: 3.6615562e+09 | M1122: 52590000000
A1123: 44952 | D1123: 1.6464772e+09 | E1123: 371090.32 | F1123: 1.6468483e+09 | G1123: 89784917 | I1123: 89784917 | J1123: 1.7366332e+09 | M1123: 54985000000
A1124: 44953 | D1124: 1898923000 | E1124: 96290.85 | F1124: 1.8990193e+09 | G1124: 41850681 | H1124: 100000000 | I1124: 141850681 | J1124: 2.04087e+09 | M1124: 57475000000
A1125: 44954 | F1125: - | G1125: 10090058 | I1125: 10090058 | J1125: 10090058 | M1125: 57475000000
A1126: 44955 | F1126: - | I1126: - | J1126: - | M1126: 57475000000
A1127: 44956 | D1127: 5077676123 | E1127: 2.9270427e+08 | F1127: 5.3703804e+09 | G1127: 136146175 | I1127: 136146175 | J1127: 5.5065266e+09 | M1127: 59881000000
A1128: 44957 | D1128: 5.1458813e+09 | E1128: 1.8176305e+08 | F1128: 5.3276443e+09 | G1128: 176745004 | I1128: 176745004 | J1128: 5.5043894e+09 | M1128: 59878000000
A1129: 44958 | D1129: 1792897223 | E1129: 1.6226212e+08 | F1129: 1.9551593e+09 | G1129: 148269949 | I1129: 148269949 | J1129: 2.1034293e+09 | M1129: 2664000000
A1130: 44959 | D1130: 7140274257 | E1130: - | F1130: 7140274257 | G1130: 72434464 | H1130: 100000000 | I1130: 172434464 | J1130: 7312708721 | M1130: 5318000000
A1131: 44960 | D1131: 1760796401 | E1131: - | F1131: 1760796401 | G1131: 84520758 | I1131: 84520758 | J1131: 1845317159 | M1131: 8061000000
A1132: 44961 | E1132: - | F1132: - | G1132: 2207400 | I1132: 2207400 | J1132: 2207400 | M1132: 8061000000
A1133: 44962 | E1133: - | F1133: - | G1133: 1958950 | I1133: 1958950 | J1133: 1958950 | M1133: 8061000000
A1134: 44963 | D1134: 3150288773 | E1134: - | F1134: 3150288773 | G1134: 63952782 | I1134: 63952782 | J1134: 3214241555 | M1134: 10703000000
A1135: 44964 | D1135: 2.5111078e+09 | E1135: - | F1135: 2.5111078e+09 | G1135: 82632292 | H1135: - | I1135: 82632292 | J1135: 2.5937401e+09 | M1135: 13356000000
A1136: 44965 | D1136: 2426320699 | F1136: 2426320699 | G1136: 55522553 | H1136: 7549351120 | I1136: 7604873673 | J1136: 10031194372 | M1136: 16022000000
A1137: 44966 | D1137: 2379283558 | E1137: 9419.46 | F1137: 2.379293e+09 | G1137: 120179476 | I1137: 120179476 | J1137: 2.4994725e+09 | M1137: 18675000000
A1138: 44967 | D1138: 1.9567507e+09 | F1138: 1.9567507e+09 | G1138: 136911441 | H1138: 100000000 | I1138: 236911441 | J1138: 2.1936621e+09 | M1138: 31692000000
A1139: 44968 | F1139: - | G1139: 3489438 | I1139: 3489438 | J1139: 3489438 | M1139: 31692000000
A1140: 44969 | F1140: - | G1140: 573623 | I1140: 573623 | J1140: 573623 | M1140: 31692000000
A1141: 44970 | D1141: 3965794075 | F1141: 3965794075 | G1141: 126802203 | I1141: 126802203 | J1141: 4092596278 | M1141: 34335000000
A1142: 44971 | D1142: 2.7345742e+09 | F1142: 2.7345742e+09 | G1142: 119353044 | I1142: 119353044 | J1142: 2.8539273e+09 | M1142: 36990000000
A1143: 44972 | D1143: 1874030560 | F1143: 1874030560 | G1143: 1.4760162e+08 | I1143: 1.4760162e+08 | J1143: 2.0216322e+09 | M1143: 39658000000
A1144: 44973 | D1144: 6401708799 | F1144: 6401708799 | G1144: 1.1266981e+08 | I1144: 1.1266981e+08 | J1144: 6.5143786e+09 | M1144: 42313000000
A1145: 44974 | D1145: 2184832574 | F1145: 2184832574 | G1145: 113544593 | H1145: 100000000 | I1145: 213544593 | J1145: 2398377167 | M1145: 45057000000
A1146: 44975 | F1146: - | G1146: 3153349 | I1146: 3153349 | J1146: 3153349 | M1146: 45057000000
A1147: 44976 | F1147: - | I1147: - | J1147: - | M1147: 45057000000
A1148: 44977 | D1148: 4931500960 | F1148: 4931500960 | G1148: 57521309 | I1148: 57521309 | J1148: 4989022269 | M1148: 47705000000
A1149: 44978 | D1149: 1.8801001e+09 | F1149: 1.8801001e+09 | G1149: 148501895 | I1149: 148501895 | J1149: 2.028602e+09 | M1149: 50364000000
A1150: 44979 | D1150: 2387909352 | F1150: 2387909352 | G1150: 325228787 | I1150: 325228787 | J1150: 2713138139 | M1150: 53035000000
A1151: 44980 | C1151: 5.4959178e+08 | D1151: 8.9834757e+08 | F1151: 8.9834757e+08 | G1151: 75723498 | H1151: - | I1151: 75723498 | J1151: 9.7407107e+08 | M1151: 55695000000
A1152: 44981 | D1152: 1382236642 | E1152: 4145750 | F1152: 1386382392 | G1152: 48027740 | H1152: 100000000 | I1152: 148027740 | J1152: 1534410132 | M1152: 58443000000
A1153: 44982 | F1153: - | G1153: 800 | I1153: 800 | J1153: 800 | M1153: 58443000000
A1154: 44983 | F1154: - | G1154: 550 | I1154: 550 | J1154: 550 | M1154: 58443000000
A1155: 44984 | D1155: 1512356699 | F1155: 1512356699 | G1155: 345081202 | I1155: 345081202 | J1155: 1857437901 | M1155: 61088000000
A1156: 44985 | D1156: 1917013983 | E1156: - | F1156: 1917013983 | G1156: 1031780139 | H1156: - | I1156: 1031780139 | J1156: 2948794122 | M1156: 63747000000
A1157: 44986 | D1157: 1223037230 | F1157: 1223037230 | G1157: 8918463 | I1157: 8918463 | J1157: 1231955693 | M1157: 2953000000
A1158: 44987 | D1158: 1876738380 | F1158: 1876738380 | G1158: 134290119 | I1158: 134290119 | J1158: 2011028499 | M1158: 5896000000
A1159: 44988 | D1159: 1645864610 | E1159: 1800 | F1159: 1645866410 | G1159: 100891551 | H1159: 100000000 | I1159: 200891551 | J1159: 1846757961 | M1159: 8926000000
A1160: 44989 | F1160: - | G1160: 2767718 | I1160: 2767718 | J1160: 2767718 | M1160: 8926000000
A1161: 44990 | F1161: - | G1161: 7502156 | I1161: 7502156 | J1161: 7502156 | M1161: 8926000000
A1162: 44991 | D1162: 1645864610 | F1162: 1645864610 | G1162: 1494900 | I1162: 1494900 | J1162: 1647359510 | M1162: 8926000000
A1163: 44992 | D1163: 2.102028e+09 | F1163: 2.102028e+09 | G1163: 987083952 | I1163: 987083952 | J1163: 3.089112e+09 | M1163: 11869000000
A1164: 44993 | D1164: 1835529349 | F1164: 1835529349 | G1164: 61756776 | I1164: 61756776 | J1164: 1897286125 | M1164: 14824000000
A1165: 44994 | D1165: 1.7443774e+09 | F1165: 1.7443774e+09 | G1165: 109585666 | H1165: 8452043680 | I1165: 8561629346 | J1165: 1.0306007e+10 | M1165: 28155000000
A1166: 44995 | D1166: 1.6698223e+09 | F1166: 1.6698223e+09 | G1166: 134358572 | H1166: 100000000 | I1166: 234358572 | J1166: 1.9041808e+09 | M1166: 31086000000
A1167: 44996 | F1167: - | G1167: 19505350 | I1167: 19505350 | J1167: 19505350 | M1167: 31086000000
A1168: 44997 | F1168: - | I1168: - | J1168: - | M1168: 31086000000
A1169: 44998 | D1169: 2369382382 | E1169: 3430238 | F1169: 2372812620 | G1169: 81055256 | H1169: - | I1169: 81055256 | J1169: 2453867876 | M1169: 34019000000
A1170: 44999 | D1170: 2498506075 | F1170: 2498506075 | G1170: 184868470 | I1170: 184868470 | J1170: 2683374545 | M1170: 36966000000
A1171: 45000 | D1171: 1.4367027e+09 | F1171: 1.4367027e+09 | G1171: 76171779 | I1171: 76171779 | J1171: 1.5128745e+09 | M1171: 39914000000
A1172: 45001 | D1172: 1.5188785e+09 | F1172: 1.5188785e+09 | G1172: 54914559 | I1172: 54914559 | J1172: 1.573793e+09 | M1172: 42860000000
A1173: 45002 | D1173: 3992925647 | E1173: 1351100 | F1173: 3994276747 | G1173: 80351305 | H1173: 100000000 | I1173: 180351305 | J1173: 4174628052 | M1173: 45894000000
A1174: 45003 | F1174: - | G1174: 12292500 | I1174: 12292500 | J1174: 12292500 | M1174: 45894000000
A1175: 45004 | F1175: - | G1175: 12855600 | I1175: 12855600 | J1175: 12855600 | M1175: 45894000000
A1176: 45005 | D1176: 2.7485267e+09 | F1176: 2.7485267e+09 | G1176: 82288756 | I1176: 82288756 | J1176: 2.8308154e+09 | M1176: 48827000000
A1177: 45006 | D1177: 1865632921 | E1177: 1100 | F1177: 1865634021 | G1177: 56208279 | H1177: - | I1177: 56208279 | J1177: 1921842300 | M1177: 51773000000
A1178: 45007 | D1178: 2095487063 | F1178: 2095487063 | G1178: 165222193 | I1178: 165222193 | J1178: 2260709256 | M1178: 54731000000
A1179: 45008 | D1179: 1457800309 | F1179: 1457800309 | G1179: 56968151 | I1179: 56968151 | J1179: 1514768460 | M1179: 57677000000
A1180: 45009 | D1180: 1.6476375e+09 | E1180: 4092148 | F1180: 1.6517297e+09 | G1180: 75219123 | H1180: 100000000 | I1180: 175219123 | J1180: 1.8269488e+09 | M1180: 60710000000
A1181: 45010 | F1181: - | G1181: 33959973 | I1181: 33959973 | J1181: 33959973 | M1181: 60710000000
A1182: 45011 | F1182: - | I1182: - | J1182: - | M1182: 60710000000
...

Sheet Revenue Codes
A1: Revenue Code | B1: Description | F1: Instructions
A2: 1001.01.00 | B2: Import Duty | F2: 1) Include all revenue items under each revenue code ensuring completeness and accuracy 2) Check if suitable revenue code exists before creating new ones. 3) New revenue codes can be added to this table from the next available line. Always remember to enter the revenue code in the usual format with a suitable short description.
A3: 1001.02.00 | B3: Export Duty
A4: 1001.04.00 | B4: PAL
A5: 1001.05.01 | B5: Cess (Import)
A6: 1001.05.02 | B6: Cess (Export)
A7: 1001.08.00 | B7: SCL
A8: 1002.01.04 | B8: VAT
A9: 1002.16.03 | B9: SSL
A10: 1002.05.01 | B10: Cigarette
A11: 1002.05.03 | B11: Petroleum Products
A12: 1002.05.04 | B12: Motor Vehicles
A13: 1002.05.99 | B13: Excise (Other)
A14: 1003.07.10 | B14: VEL
... A29: 1001.03.00 | B29: IECD License Fee

Sheet Holidays
A1: Date | B1: Day | C1: Holiday Name | D1: Holiday Type | H1: Instructions
A2: 43840 | B2: Friday | C2: Duruthu Full Moon Poya Day | D2: Public & Bank | H2: 1) Please update this table to automatically highlight the holidays. 2) Any holidays not noted in the table can be added at the end. Order of table does not have an impact on functionality. 3) This table helps understands daily revenue collections. It does not have a bearing on the functionality of the Excel
A3: 43845 | B3: Wednesday | C3: Tamil Thai Pongal Day | D3: Public, Bank & Mercantile
A4: 43865 | B4: Tuesday | C4: National Day | D4: Public, Bank & Mercantile
A5: 43869 | B5: Saturday | C5: Navam Full Moon Poya Day | D5: Public & Bank
A6: 43882 | B6: Friday | C6: Mahasivarathri Day | D6: Public & Bank
A7: 43899 | B7: Monday | C7: Medin Full Moon Poya Day | D7: Public & Bank
A8: 43928 | B8: Tuesday | C8: Bak Full Moon Poya Day | D8: Public & Bank
A9: 43931 | B9: Friday | C9: Good Friday | D9: Public & Bank
A10: 43933 | B10: Sunday | C10: Day prior to Sinhala & Tamil New Year Day | D10: Public, Bank & Mercantile
A11: 43934 | B11: Monday | C11: Sinhala & Tamil New Year Day | D11: Public, Bank & Mercantile
A12: 43935 | B12: Tuesday | C12: Special Bank Holiday | D12: Bank
A13: 43952 | B13: Friday | C13: May Day (Labour Day) | D13: Public, Bank & Mercantile
A14: 43958 | B14: Thursday | C14: Vesak Full Moon Poya Day | D14: Public & Bank
... A187: 46381 | B187: Friday | C187: Christmas Day | D187: Public, Bank & Mercantile
